{
 "tomado": "2026-07-22T15:30:01",
 "motivo": "curado de presentaciones y unidades - CURADO_PENDIENTE.md",
 "filas": 167,
 "datos": [
  {
   "id": "31d84a13-ab2c-493b-b2ca-b78368f9a95b",
   "presupuesto_id": "f2574ab3-b474-4a34-946f-75bc0a94298b",
   "texto_original": "ARENA BOLS",
   "texto_normalizado": "arena bols",
   "marca": null,
   "unidad": null,
   "cantidad": 23.0,
   "precio": 978287.67,
   "codigo_material": "CONS108",
   "pendiente_id": null,
   "score_match": 84,
   "estado_match": "REVISAR",
   "origen_match": "fuzzy",
   "created_at": "2026-07-13T11:22:08.990508+00:00"
  },
  {
   "id": "648b7c75-c68d-481e-821a-fb17d2efe625",
   "presupuesto_id": "f2574ab3-b474-4a34-946f-75bc0a94298b",
   "texto_original": "VARILLA 6",
   "texto_normalizado": "varilla 6",
   "marca": null,
   "unidad": null,
   "cantidad": 107.0,
   "precio": 648848.56,
   "codigo_material": "A006",
   "pendiente_id": null,
   "score_match": 84,
   "estado_match": "REVISAR",
   "origen_match": "fuzzy",
   "created_at": "2026-07-13T11:22:08.990508+00:00"
  },
  {
   "id": "3ed26df0-7987-4c98-9b9e-bab8408217c6",
   "presupuesto_id": "f2574ab3-b474-4a34-946f-75bc0a94298b",
   "texto_original": "VARILLA 12",
   "texto_normalizado": "varilla 12",
   "marca": null,
   "unidad": null,
   "cantidad": 8.0,
   "precio": 188235.29,
   "codigo_material": "A006",
   "pendiente_id": null,
   "score_match": 84,
   "estado_match": "REVISAR",
   "origen_match": "fuzzy",
   "created_at": "2026-07-13T11:22:08.990508+00:00"
  },
  {
   "id": "3ae32644-bc27-4269-8380-2ec33934a142",
   "presupuesto_id": "f2574ab3-b474-4a34-946f-75bc0a94298b",
   "texto_original": "LADRILLO RE",
   "texto_normalizado": "ladrillo re",
   "marca": null,
   "unidad": null,
   "cantidad": 208.0,
   "precio": 860153.41,
   "codigo_material": "CONS125",
   "pendiente_id": null,
   "score_match": 84,
   "estado_match": "REVISAR",
   "origen_match": "fuzzy",
   "created_at": "2026-07-13T11:22:08.990508+00:00"
  },
  {
   "id": "810e0054-52bf-4e92-ac0a-f3c3f0e1ff7f",
   "presupuesto_id": "f2574ab3-b474-4a34-946f-75bc0a94298b",
   "texto_original": "VARILLA 8",
   "texto_normalizado": "varilla 8",
   "marca": null,
   "unidad": null,
   "cantidad": 58.0,
   "precio": 619373.31,
   "codigo_material": "A006",
   "pendiente_id": null,
   "score_match": 84,
   "estado_match": "REVISAR",
   "origen_match": "fuzzy",
   "created_at": "2026-07-13T11:22:08.990508+00:00"
  },
  {
   "id": "dbaa1023-09ad-4ccc-8879-a170d3ca364b",
   "presupuesto_id": "df6b50c0-5c16-4733-814f-e25a0db697a8",
   "texto_original": "MTS",
   "texto_normalizado": "mts",
   "marca": null,
   "unidad": null,
   "cantidad": 1.0,
   "precio": 156380.09,
   "codigo_material": "A001",
   "pendiente_id": null,
   "score_match": 84,
   "estado_match": "REVISAR",
   "origen_match": "fuzzy",
   "created_at": "2026-07-13T11:22:10.148594+00:00"
  },
  {
   "id": "31791459-a3b0-4bd4-80a7-1b0b8ff16d11",
   "presupuesto_id": "f073b605-d5d8-428a-9c3d-fe9d30ffc04d",
   "texto_original": "ACUSTIVER R400 LANA DE VIDRIO 70MM 15.60 M2",
   "texto_normalizado": "acustiver r400 lana de vidrio 70mm 15.60 m2",
   "marca": null,
   "unidad": null,
   "cantidad": 8.0,
   "precio": 118747.24,
   "codigo_material": "AISL113",
   "pendiente_id": null,
   "score_match": 100,
   "estado_match": "CONFIRMADO",
   "origen_match": "usuario",
   "created_at": "2026-07-14T00:46:32.666314+00:00"
  },
  {
   "id": "8ec4e044-0154-41a5-a398-4d84252aaad8",
   "presupuesto_id": "f073b605-d5d8-428a-9c3d-fe9d30ffc04d",
   "texto_original": "VARILLA ROSCADA FTR M12X160",
   "texto_normalizado": "varilla roscada ftr m12x160",
   "marca": null,
   "unidad": null,
   "cantidad": 52.0,
   "precio": 2629.8,
   "codigo_material": "A006",
   "pendiente_id": null,
   "score_match": 76,
   "estado_match": "CONFIRMADO",
   "origen_match": "usuario",
   "created_at": "2026-07-14T00:46:32.666314+00:00"
  },
  {
   "id": "c461af1c-faba-4820-b0ac-63145e7b8fa3",
   "presupuesto_id": "f073b605-d5d8-428a-9c3d-fe9d30ffc04d",
   "texto_original": "CINTA REGULAR TYPAR",
   "texto_normalizado": "cinta regular typar",
   "marca": null,
   "unidad": null,
   "cantidad": 29.0,
   "precio": 48380.29,
   "codigo_material": "EST110",
   "pendiente_id": null,
   "score_match": 73,
   "estado_match": "CONFIRMADO",
   "origen_match": "usuario",
   "created_at": "2026-07-14T00:46:32.666314+00:00"
  },
  {
   "id": "a5d13a42-0d55-47c9-af24-81a5a4a691a8",
   "presupuesto_id": "836af4a1-ec4e-4079-bfbf-7ce6a1ff8374",
   "texto_original": "WATERPLAST CAMARA LODOS P/BIO 100L",
   "texto_normalizado": "waterplast camara lodos p/bio 100l",
   "marca": null,
   "unidad": null,
   "cantidad": 1.0,
   "precio": 84268.9,
   "codigo_material": "INSTS008",
   "pendiente_id": null,
   "score_match": 100,
   "estado_match": "CONFIRMADO",
   "origen_match": "usuario",
   "created_at": "2026-07-13T23:16:39.56214+00:00"
  },
  {
   "id": "d15ac261-7c55-49f5-a964-fad0e368bb57",
   "presupuesto_id": "836af4a1-ec4e-4079-bfbf-7ce6a1ff8374",
   "texto_original": "PRESURIZADOR \"TANGO 20 SFL\" ROWA",
   "texto_normalizado": "presurizador \"tango 20 sfl\" rowa",
   "marca": null,
   "unidad": null,
   "cantidad": 1.0,
   "precio": 535571.36,
   "codigo_material": "INSTS016",
   "pendiente_id": null,
   "score_match": 100,
   "estado_match": "CONFIRMADO",
   "origen_match": "usuario",
   "created_at": "2026-07-13T23:16:39.56214+00:00"
  },
  {
   "id": "83cfd35d-c231-4efc-87cc-d2d53364e9c0",
   "presupuesto_id": "836af4a1-ec4e-4079-bfbf-7ce6a1ff8374",
   "texto_original": "CODO MH 50X45 DURATOP",
   "texto_normalizado": "codo mh 50x45 duratop",
   "marca": null,
   "unidad": null,
   "cantidad": 6.0,
   "precio": 1101.48,
   "codigo_material": "INSTS036",
   "pendiente_id": null,
   "score_match": 89,
   "estado_match": "CONFIRMADO",
   "origen_match": "usuario",
   "created_at": "2026-07-13T23:16:39.56214+00:00"
  },
  {
   "id": "022d3b5f-a38f-4520-9c00-7e08418d98e6",
   "presupuesto_id": "836af4a1-ec4e-4079-bfbf-7ce6a1ff8374",
   "texto_original": "CODO MH 63X45 DURATOP",
   "texto_normalizado": "codo mh 63x45 duratop",
   "marca": null,
   "unidad": null,
   "cantidad": 6.0,
   "precio": 1186.64,
   "codigo_material": "INSTS036",
   "pendiente_id": null,
   "score_match": 89,
   "estado_match": "CONFIRMADO",
   "origen_match": "usuario",
   "created_at": "2026-07-13T23:16:39.56214+00:00"
  },
  {
   "id": "c6ce8691-55c9-4200-97c1-cd629ebd4bb9",
   "presupuesto_id": "836af4a1-ec4e-4079-bfbf-7ce6a1ff8374",
   "texto_original": "CODO MH 110X45 DURATOP",
   "texto_normalizado": "codo mh 110x45 duratop",
   "marca": null,
   "unidad": null,
   "cantidad": 5.0,
   "precio": 2138.44,
   "codigo_material": "INSTS038",
   "pendiente_id": null,
   "score_match": 92,
   "estado_match": "CONFIRMADO",
   "origen_match": "usuario",
   "created_at": "2026-07-13T23:16:39.56214+00:00"
  },
  {
   "id": "a9de359c-35ec-466b-8768-362465871499",
   "presupuesto_id": "836af4a1-ec4e-4079-bfbf-7ce6a1ff8374",
   "texto_original": "CODO MH 50X90 DURATOP",
   "texto_normalizado": "codo mh 50x90 duratop",
   "marca": null,
   "unidad": null,
   "cantidad": 4.0,
   "precio": 1101.48,
   "codigo_material": "INSTS036",
   "pendiente_id": null,
   "score_match": 89,
   "estado_match": "CONFIRMADO",
   "origen_match": "usuario",
   "created_at": "2026-07-13T23:16:39.56214+00:00"
  },
  {
   "id": "72e0dd14-7509-436d-85dc-aa1223c9a27a",
   "presupuesto_id": "836af4a1-ec4e-4079-bfbf-7ce6a1ff8374",
   "texto_original": "RAMAL 110X110 A 45 DURATOP",
   "texto_normalizado": "ramal 110x110 a 45 duratop",
   "marca": null,
   "unidad": null,
   "cantidad": 1.0,
   "precio": 5776.07,
   "codigo_material": "INSTS050",
   "pendiente_id": null,
   "score_match": 100,
   "estado_match": "CONFIRMADO",
   "origen_match": "usuario",
   "created_at": "2026-07-13T23:16:39.56214+00:00"
  },
  {
   "id": "304c154e-4bb6-4ae8-a924-6706dcf3c802",
   "presupuesto_id": "836af4a1-ec4e-4079-bfbf-7ce6a1ff8374",
   "texto_original": "A.SYSTEM UNION NORMAL 32",
   "texto_normalizado": "a.system union normal 32",
   "marca": null,
   "unidad": null,
   "cantidad": 16.0,
   "precio": 795.44,
   "codigo_material": "INSTS080",
   "pendiente_id": null,
   "score_match": 88,
   "estado_match": "CONFIRMADO",
   "origen_match": "usuario",
   "created_at": "2026-07-13T23:16:39.56214+00:00"
  },
  {
   "id": "571ce57b-a236-4d3f-b488-f6b4fa1766e8",
   "presupuesto_id": "836af4a1-ec4e-4079-bfbf-7ce6a1ff8374",
   "texto_original": "A.SYSTEM UNION NORMAL 50",
   "texto_normalizado": "a.system union normal 50",
   "marca": null,
   "unidad": null,
   "cantidad": 4.0,
   "precio": 2703.37,
   "codigo_material": "INSTS054",
   "pendiente_id": null,
   "score_match": 100,
   "estado_match": "CONFIRMADO",
   "origen_match": "usuario",
   "created_at": "2026-07-13T23:16:39.56214+00:00"
  },
  {
   "id": "1919e3da-1dad-411c-b55c-357d8d1ef352",
   "presupuesto_id": "836af4a1-ec4e-4079-bfbf-7ce6a1ff8374",
   "texto_original": "A.SYSTEM TEE NORMAL 20",
   "texto_normalizado": "a.system tee normal 20",
   "marca": null,
   "unidad": null,
   "cantidad": 6.0,
   "precio": 515.67,
   "codigo_material": "INSTS093",
   "pendiente_id": null,
   "score_match": 85,
   "estado_match": "CONFIRMADO",
   "origen_match": "usuario",
   "created_at": "2026-07-13T23:16:39.56214+00:00"
  },
  {
   "id": "b9d402c5-3978-4f61-a461-7848e315e4da",
   "presupuesto_id": "836af4a1-ec4e-4079-bfbf-7ce6a1ff8374",
   "texto_original": "A.SYSTEM TAPA HEMBRA 50",
   "texto_normalizado": "a.system tapa hembra 50",
   "marca": null,
   "unidad": null,
   "cantidad": 2.0,
   "precio": 2692.91,
   "codigo_material": "INSTS062",
   "pendiente_id": null,
   "score_match": 100,
   "estado_match": "CONFIRMADO",
   "origen_match": "usuario",
   "created_at": "2026-07-13T23:16:39.56214+00:00"
  },
  {
   "id": "51ceb103-241b-4207-b46d-dd76f335afb0",
   "presupuesto_id": "836af4a1-ec4e-4079-bfbf-7ce6a1ff8374",
   "texto_original": "A.SYSTEM UNION DOBLE PLASTICA 32",
   "texto_normalizado": "a.system union doble plastica 32",
   "marca": null,
   "unidad": null,
   "cantidad": 4.0,
   "precio": 3134.47,
   "codigo_material": "INSTS123",
   "pendiente_id": null,
   "score_match": 86,
   "estado_match": "CONFIRMADO",
   "origen_match": "usuario",
   "created_at": "2026-07-13T23:16:39.56214+00:00"
  },
  {
   "id": "b480fb98-3cfa-499c-9b8e-9d105367922b",
   "presupuesto_id": "836af4a1-ec4e-4079-bfbf-7ce6a1ff8374",
   "texto_original": "SIGAS CAÑO 20 X 4 MTS",
   "texto_normalizado": "sigas caño 20 x 4 mts",
   "marca": null,
   "unidad": null,
   "cantidad": 3.0,
   "precio": 13657.58,
   "codigo_material": "INSTS140",
   "pendiente_id": null,
   "score_match": 98,
   "estado_match": "CONFIRMADO",
   "origen_match": "usuario",
   "created_at": "2026-07-13T23:16:39.56214+00:00"
  },
  {
   "id": "7143e1a9-e0ab-4edc-a310-8b7af4543636",
   "presupuesto_id": "836af4a1-ec4e-4079-bfbf-7ce6a1ff8374",
   "texto_original": "CAMARA DESEGRASADORA GRANDE GRIS",
   "texto_normalizado": "camara desegrasadora grande gris",
   "marca": null,
   "unidad": null,
   "cantidad": 1.0,
   "precio": 91529.36,
   "codigo_material": "INSTS004",
   "pendiente_id": null,
   "score_match": 62,
   "estado_match": "CONFIRMADO",
   "origen_match": "usuario",
   "created_at": "2026-07-13T23:16:39.56214+00:00"
  },
  {
   "id": "72693aa5-5bf3-4efc-904b-6cc65a0b6f9a",
   "presupuesto_id": "836af4a1-ec4e-4079-bfbf-7ce6a1ff8374",
   "texto_original": "MANGUITO REPARACION 110 DURATOP",
   "texto_normalizado": "manguito reparacion 110 duratop",
   "marca": null,
   "unidad": null,
   "cantidad": 20.0,
   "precio": 2693.06,
   "codigo_material": "INSTS052",
   "pendiente_id": null,
   "score_match": 77,
   "estado_match": "CONFIRMADO",
   "origen_match": "usuario",
   "created_at": "2026-07-13T23:16:39.56214+00:00"
  },
  {
   "id": "7bb29d10-cca2-46af-b9c6-317e957db1ba",
   "presupuesto_id": "836af4a1-ec4e-4079-bfbf-7ce6a1ff8374",
   "texto_original": "MANGUITO REPARACION 63 DURATOP",
   "texto_normalizado": "manguito reparacion 63 duratop",
   "marca": null,
   "unidad": null,
   "cantidad": 15.0,
   "precio": 1465.6,
   "codigo_material": "INSTS053",
   "pendiente_id": null,
   "score_match": 78,
   "estado_match": "CONFIRMADO",
   "origen_match": "usuario",
   "created_at": "2026-07-13T23:16:39.56214+00:00"
  },
  {
   "id": "ee22684a-5a60-4256-941d-641b55326b66",
   "presupuesto_id": "836af4a1-ec4e-4079-bfbf-7ce6a1ff8374",
   "texto_original": "CANO DURATOP 110X1.00 MTS",
   "texto_normalizado": "cano duratop 110x1.00 mts",
   "marca": null,
   "unidad": null,
   "cantidad": 1.0,
   "precio": 7586.95,
   "codigo_material": "INSTS052",
   "pendiente_id": "663c2bc5-8e03-492a-9b19-329b659ddcfe",
   "score_match": 83,
   "estado_match": "REVISAR",
   "origen_match": "fuzzy",
   "created_at": "2026-07-13T23:16:39.56214+00:00"
  },
  {
   "id": "f6099380-ba55-4965-8b5b-92c53ec5f4db",
   "presupuesto_id": "836af4a1-ec4e-4079-bfbf-7ce6a1ff8374",
   "texto_original": "CANO DURATOP 110X4.00 MTS",
   "texto_normalizado": "cano duratop 110x4.00 mts",
   "marca": null,
   "unidad": null,
   "cantidad": 39.0,
   "precio": 19817.76,
   "codigo_material": "INSTS052",
   "pendiente_id": "f1794bcf-fbf7-43c7-abee-acb72d072e96",
   "score_match": 83,
   "estado_match": "REVISAR",
   "origen_match": "fuzzy",
   "created_at": "2026-07-13T23:16:39.56214+00:00"
  },
  {
   "id": "d4619dfd-65e5-4ac6-9a9f-49663d373ec4",
   "presupuesto_id": "836af4a1-ec4e-4079-bfbf-7ce6a1ff8374",
   "texto_original": "CANO DURATOP 63X1.00 MTS",
   "texto_normalizado": "cano duratop 63x1.00 mts",
   "marca": null,
   "unidad": null,
   "cantidad": 9.0,
   "precio": 3838.14,
   "codigo_material": "INSTS053",
   "pendiente_id": "b923911e-2367-4e49-bf8b-917b00e99def",
   "score_match": 78,
   "estado_match": "REVISAR",
   "origen_match": "fuzzy",
   "created_at": "2026-07-13T23:16:39.56214+00:00"
  },
  {
   "id": "02709c80-1e66-450b-8d46-e7e7378f2a26",
   "presupuesto_id": "836af4a1-ec4e-4079-bfbf-7ce6a1ff8374",
   "texto_original": "CANO DURATOP 50X1.00 MTS",
   "texto_normalizado": "cano duratop 50x1.00 mts",
   "marca": null,
   "unidad": null,
   "cantidad": 8.0,
   "precio": 2940.08,
   "codigo_material": "INSTS054",
   "pendiente_id": "478928ad-58b3-4597-9c8d-cb2c6ae88902",
   "score_match": 78,
   "estado_match": "REVISAR",
   "origen_match": "fuzzy",
   "created_at": "2026-07-13T23:16:39.56214+00:00"
  },
  {
   "id": "1dce2672-f090-4394-9a9e-6f8e081bfc54",
   "presupuesto_id": "836af4a1-ec4e-4079-bfbf-7ce6a1ff8374",
   "texto_original": "CANO DURATOP 40X1.00 MTS",
   "texto_normalizado": "cano duratop 40x1.00 mts",
   "marca": null,
   "unidad": null,
   "cantidad": 7.0,
   "precio": 2323.05,
   "codigo_material": "INSTS054",
   "pendiente_id": "cb808966-290d-48c9-bcdb-b50ffca48795",
   "score_match": 78,
   "estado_match": "REVISAR",
   "origen_match": "fuzzy",
   "created_at": "2026-07-13T23:16:39.56214+00:00"
  },
  {
   "id": "a104d22b-77ed-4a36-af3d-0a74264db93b",
   "presupuesto_id": "836af4a1-ec4e-4079-bfbf-7ce6a1ff8374",
   "texto_original": "CANO DURATOP 40X2.00 MTS",
   "texto_normalizado": "cano duratop 40x2.00 mts",
   "marca": null,
   "unidad": null,
   "cantidad": 4.0,
   "precio": 3886.08,
   "codigo_material": "INSTS054",
   "pendiente_id": "33c6666a-2e17-4e59-9fda-8857d2d07fbe",
   "score_match": 78,
   "estado_match": "REVISAR",
   "origen_match": "fuzzy",
   "created_at": "2026-07-13T23:16:39.56214+00:00"
  },
  {
   "id": "d166c7fe-8cf5-4081-b70b-435fcc3347ec",
   "presupuesto_id": "836af4a1-ec4e-4079-bfbf-7ce6a1ff8374",
   "texto_original": "CANO DURATOP 40X4.00 MTS",
   "texto_normalizado": "cano duratop 40x4.00 mts",
   "marca": null,
   "unidad": null,
   "cantidad": 2.0,
   "precio": 7054.01,
   "codigo_material": "INSTS065",
   "pendiente_id": "ddb7ee7f-4492-45eb-aafe-bde35aec5b1e",
   "score_match": 82,
   "estado_match": "REVISAR",
   "origen_match": "fuzzy",
   "created_at": "2026-07-13T23:16:39.56214+00:00"
  },
  {
   "id": "5b79c91d-2193-47d7-8d79-515079b8a430",
   "presupuesto_id": "836af4a1-ec4e-4079-bfbf-7ce6a1ff8374",
   "texto_original": "PILETA PATIO 110 CHICA DURATOP",
   "texto_normalizado": "pileta patio 110 chica duratop",
   "marca": null,
   "unidad": null,
   "cantidad": 3.0,
   "precio": 6759.63,
   "codigo_material": "INSTS056",
   "pendiente_id": null,
   "score_match": 77,
   "estado_match": "CONFIRMADO",
   "origen_match": "usuario",
   "created_at": "2026-07-13T23:16:39.56214+00:00"
  },
  {
   "id": "cbb1633c-b600-4ff2-89f5-30aaf5fde8c9",
   "presupuesto_id": "836af4a1-ec4e-4079-bfbf-7ce6a1ff8374",
   "texto_original": "SOLUCION SILICONADA AEROSOL 400CC",
   "texto_normalizado": "solucion siliconada aerosol 400cc",
   "marca": null,
   "unidad": null,
   "cantidad": 1.0,
   "precio": 4759.76,
   "codigo_material": "INSTS069",
   "pendiente_id": null,
   "score_match": 69,
   "estado_match": "CONFIRMADO",
   "origen_match": "usuario",
   "created_at": "2026-07-13T23:16:39.56214+00:00"
  },
  {
   "id": "5a6038f2-9bc8-4ae8-9d21-f8e04dcf7c83",
   "presupuesto_id": "836af4a1-ec4e-4079-bfbf-7ce6a1ff8374",
   "texto_original": "A.SYSTEM CANO PN20 CALIENTE 20X4 M",
   "texto_normalizado": "a.system cano pn20 caliente 20x4 m",
   "marca": null,
   "unidad": null,
   "cantidad": 6.0,
   "precio": 5665.91,
   "codigo_material": "INSTS074",
   "pendiente_id": null,
   "score_match": 75,
   "estado_match": "CONFIRMADO",
   "origen_match": "usuario",
   "created_at": "2026-07-13T23:16:39.56214+00:00"
  },
  {
   "id": "41b9faf9-ad20-4c90-a029-94c49e4f3922",
   "presupuesto_id": "836af4a1-ec4e-4079-bfbf-7ce6a1ff8374",
   "texto_original": "A.SYSTEM CANO PN20 CALIENTE 25X4 M",
   "texto_normalizado": "a.system cano pn20 caliente 25x4 m",
   "marca": null,
   "unidad": null,
   "cantidad": 16.0,
   "precio": 8239.23,
   "codigo_material": "INSTS075",
   "pendiente_id": null,
   "score_match": 75,
   "estado_match": "CONFIRMADO",
   "origen_match": "usuario",
   "created_at": "2026-07-13T23:16:39.56214+00:00"
  },
  {
   "id": "812656f6-be27-4292-be9c-1e8ee75eab80",
   "presupuesto_id": "836af4a1-ec4e-4079-bfbf-7ce6a1ff8374",
   "texto_original": "A.SYSTEM CANO PN20 CALIENTE 50X4 M",
   "texto_normalizado": "a.system cano pn20 caliente 50x4 m",
   "marca": null,
   "unidad": null,
   "cantidad": 3.0,
   "precio": 28175.64,
   "codigo_material": "INSTS077",
   "pendiente_id": null,
   "score_match": 75,
   "estado_match": "CONFIRMADO",
   "origen_match": "usuario",
   "created_at": "2026-07-13T23:16:39.56214+00:00"
  },
  {
   "id": "cbceadbe-4a51-47f7-aa02-d4e2490c0701",
   "presupuesto_id": "836af4a1-ec4e-4079-bfbf-7ce6a1ff8374",
   "texto_original": "A.SYSTEM TEE RED.CENTRAL 25X20",
   "texto_normalizado": "a.system tee red.central 25x20",
   "marca": null,
   "unidad": null,
   "cantidad": 2.0,
   "precio": 878.05,
   "codigo_material": "INSTS099",
   "pendiente_id": null,
   "score_match": 71,
   "estado_match": "CONFIRMADO",
   "origen_match": "usuario",
   "created_at": "2026-07-13T23:16:39.56214+00:00"
  },
  {
   "id": "f6991119-72c1-442c-88ea-2a19126edbd1",
   "presupuesto_id": "836af4a1-ec4e-4079-bfbf-7ce6a1ff8374",
   "texto_original": "A.SYSTEM CURVA SOBREPASO 20",
   "texto_normalizado": "a.system curva sobrepaso 20",
   "marca": null,
   "unidad": null,
   "cantidad": 6.0,
   "precio": 1095.77,
   "codigo_material": "INSTS125",
   "pendiente_id": null,
   "score_match": 64,
   "estado_match": "CONFIRMADO",
   "origen_match": "usuario",
   "created_at": "2026-07-13T23:16:39.56214+00:00"
  },
  {
   "id": "33592f11-2220-4fd9-8d07-6cef5b4f7ab9",
   "presupuesto_id": "836af4a1-ec4e-4079-bfbf-7ce6a1ff8374",
   "texto_original": "A.SYSTEM CURVA SOBREPASO 25",
   "texto_normalizado": "a.system curva sobrepaso 25",
   "marca": null,
   "unidad": null,
   "cantidad": 2.0,
   "precio": 1649.67,
   "codigo_material": "INSTS126",
   "pendiente_id": null,
   "score_match": 64,
   "estado_match": "CONFIRMADO",
   "origen_match": "usuario",
   "created_at": "2026-07-13T23:16:39.56214+00:00"
  },
  {
   "id": "c82e1b25-7b66-4f83-a742-3d177b84b3ae",
   "presupuesto_id": "836af4a1-ec4e-4079-bfbf-7ce6a1ff8374",
   "texto_original": "CAÑO PVC CLOACAL JP 160X4MT TIGRE",
   "texto_normalizado": "caño pvc cloacal jp 160x4mt tigre",
   "marca": null,
   "unidad": null,
   "cantidad": 1.0,
   "precio": 39277.86,
   "codigo_material": "INSTS172",
   "pendiente_id": null,
   "score_match": 85,
   "estado_match": "CONFIRMADO",
   "origen_match": "usuario",
   "created_at": "2026-07-13T23:16:39.56214+00:00"
  },
  {
   "id": "31668550-8f12-4138-9fbb-540f11f57bd1",
   "presupuesto_id": "836af4a1-ec4e-4079-bfbf-7ce6a1ff8374",
   "texto_original": "SOBRE PILETA 110 C/5 ENTRADAS",
   "texto_normalizado": "sobre pileta 110 c/5 entradas",
   "marca": null,
   "unidad": null,
   "cantidad": 1.0,
   "precio": 8567.39,
   "codigo_material": "INSTS056",
   "pendiente_id": "4dcfacf5-6e12-4f86-874f-5a26281d9ff0",
   "score_match": 79,
   "estado_match": "REVISAR",
   "origen_match": "fuzzy",
   "created_at": "2026-07-13T23:16:39.56214+00:00"
  },
  {
   "id": "251c9316-de85-4dae-b494-7c67e63345e7",
   "presupuesto_id": "836af4a1-ec4e-4079-bfbf-7ce6a1ff8374",
   "texto_original": "SYST UNION DOB.MIXTA C/BRI.50X11/2",
   "texto_normalizado": "syst union dob.mixta c/bri.50x11/2",
   "marca": null,
   "unidad": null,
   "cantidad": 2.0,
   "precio": 41782.29,
   "codigo_material": "INSTS053",
   "pendiente_id": "981d0df1-9df7-49e5-a4dd-9117be380c62",
   "score_match": 77,
   "estado_match": "REVISAR",
   "origen_match": "fuzzy",
   "created_at": "2026-07-13T23:16:39.56214+00:00"
  },
  {
   "id": "bacc14aa-7cbc-44bf-8f3a-e3a801bfbf68",
   "presupuesto_id": "c9a33791-3d5b-4769-8179-2e4696b2e98e",
   "texto_original": "ROWA TANGO 20 SFL",
   "texto_normalizado": "rowa tango 20 sfl",
   "marca": null,
   "unidad": null,
   "cantidad": 1.0,
   "precio": 577419.03,
   "codigo_material": "INSTS016",
   "pendiente_id": null,
   "score_match": 100,
   "estado_match": "CONFIRMADO",
   "origen_match": "usuario",
   "created_at": "2026-07-13T23:16:41.843508+00:00"
  },
  {
   "id": "f733b28e-33ff-4687-b6ed-28fce98f513e",
   "presupuesto_id": "c9a33791-3d5b-4769-8179-2e4696b2e98e",
   "texto_original": "RAMAL 2023 SIMPLE 45 MH DE 110 AWA",
   "texto_normalizado": "ramal 2023 simple 45 mh de 110 awa",
   "marca": null,
   "unidad": null,
   "cantidad": 1.0,
   "precio": 6681.72,
   "codigo_material": "INSTS050",
   "pendiente_id": null,
   "score_match": 92,
   "estado_match": "CONFIRMADO",
   "origen_match": "usuario",
   "created_at": "2026-07-13T23:16:41.843508+00:00"
  },
  {
   "id": "098b55a4-3e12-4057-846f-48a936089106",
   "presupuesto_id": "c9a33791-3d5b-4769-8179-2e4696b2e98e",
   "texto_original": "TAPA HEMBRA 2037 50 AWA",
   "texto_normalizado": "tapa hembra 2037 50 awa",
   "marca": null,
   "unidad": null,
   "cantidad": 3.0,
   "precio": 828.12,
   "codigo_material": "INSTS062",
   "pendiente_id": null,
   "score_match": 100,
   "estado_match": "CONFIRMADO",
   "origen_match": "usuario",
   "created_at": "2026-07-13T23:16:41.843508+00:00"
  },
  {
   "id": "2c4cf3bd-4758-4a1d-b66a-19f112bb8cb6",
   "presupuesto_id": "c9a33791-3d5b-4769-8179-2e4696b2e98e",
   "texto_original": "UNION NORMAL 32 ACQUA",
   "texto_normalizado": "union normal 32 acqua",
   "marca": null,
   "unidad": null,
   "cantidad": 16.0,
   "precio": 942.13,
   "codigo_material": "INSTS080",
   "pendiente_id": null,
   "score_match": 100,
   "estado_match": "CONFIRMADO",
   "origen_match": "usuario",
   "created_at": "2026-07-13T23:16:41.843508+00:00"
  },
  {
   "id": "00b839fd-914c-4c17-ab0c-18446e0db681",
   "presupuesto_id": "c9a33791-3d5b-4769-8179-2e4696b2e98e",
   "texto_original": "UNION NORMAL 50 ACQUA",
   "texto_normalizado": "union normal 50 acqua",
   "marca": null,
   "unidad": null,
   "cantidad": 4.0,
   "precio": 3204.37,
   "codigo_material": "INSTS054",
   "pendiente_id": null,
   "score_match": 100,
   "estado_match": "CONFIRMADO",
   "origen_match": "usuario",
   "created_at": "2026-07-13T23:16:41.843508+00:00"
  },
  {
   "id": "501bbdcd-b1a1-4696-a4a4-fa5f4027859b",
   "presupuesto_id": "c9a33791-3d5b-4769-8179-2e4696b2e98e",
   "texto_original": "TEE NORMAL 20 ACQUA",
   "texto_normalizado": "tee normal 20 acqua",
   "marca": null,
   "unidad": null,
   "cantidad": 6.0,
   "precio": 611.45,
   "codigo_material": "INSTS093",
   "pendiente_id": null,
   "score_match": 91,
   "estado_match": "CONFIRMADO",
   "origen_match": "usuario",
   "created_at": "2026-07-13T23:16:41.843508+00:00"
  },
  {
   "id": "16a239b9-e334-44c9-bb4c-a362d25439d6",
   "presupuesto_id": "c9a33791-3d5b-4769-8179-2e4696b2e98e",
   "texto_original": "TEE NORMAL 25 ACQUA",
   "texto_normalizado": "tee normal 25 acqua",
   "marca": null,
   "unidad": null,
   "cantidad": 4.0,
   "precio": 954.95,
   "codigo_material": "INSTS093",
   "pendiente_id": null,
   "score_match": 91,
   "estado_match": "CONFIRMADO",
   "origen_match": "usuario",
   "created_at": "2026-07-13T23:16:41.843508+00:00"
  },
  {
   "id": "7794e434-085e-4021-9694-93bc2182716a",
   "presupuesto_id": "c9a33791-3d5b-4769-8179-2e4696b2e98e",
   "texto_original": "TEE NORMAL 32 ACQUA",
   "texto_normalizado": "tee normal 32 acqua",
   "marca": null,
   "unidad": null,
   "cantidad": 2.0,
   "precio": 1387.1,
   "codigo_material": "INSTS093",
   "pendiente_id": null,
   "score_match": 91,
   "estado_match": "CONFIRMADO",
   "origen_match": "usuario",
   "created_at": "2026-07-13T23:16:41.843508+00:00"
  },
  {
   "id": "929d21d0-7328-40ed-8f85-b20936cd680a",
   "presupuesto_id": "c9a33791-3d5b-4769-8179-2e4696b2e98e",
   "texto_original": "CODO A 90 RH 25 X 1/2 ACQUA",
   "texto_normalizado": "codo a 90 rh 25 x 1/2 acqua",
   "marca": null,
   "unidad": null,
   "cantidad": 2.0,
   "precio": 3124.74,
   "codigo_material": "INSTS106",
   "pendiente_id": null,
   "score_match": 88,
   "estado_match": "CONFIRMADO",
   "origen_match": "usuario",
   "created_at": "2026-07-13T23:16:41.843508+00:00"
  },
  {
   "id": "5aac416a-e145-4ce7-97fa-e990fa20df1a",
   "presupuesto_id": "c9a33791-3d5b-4769-8179-2e4696b2e98e",
   "texto_original": "CODO A 90 RM 20 X 1/2 ACQUA",
   "texto_normalizado": "codo a 90 rm 20 x 1/2 acqua",
   "marca": null,
   "unidad": null,
   "cantidad": 15.0,
   "precio": 3364.59,
   "codigo_material": "INSTS106",
   "pendiente_id": null,
   "score_match": 94,
   "estado_match": "CONFIRMADO",
   "origen_match": "usuario",
   "created_at": "2026-07-13T23:16:41.843508+00:00"
  },
  {
   "id": "4c384016-0cdb-46e1-9bd6-5a9375236f8a",
   "presupuesto_id": "c9a33791-3d5b-4769-8179-2e4696b2e98e",
   "texto_original": "UNION DOBLE 32 ACQUA",
   "texto_normalizado": "union doble 32 acqua",
   "marca": null,
   "unidad": null,
   "cantidad": 4.0,
   "precio": 3716.05,
   "codigo_material": "INSTS080",
   "pendiente_id": null,
   "score_match": 100,
   "estado_match": "CONFIRMADO",
   "origen_match": "usuario",
   "created_at": "2026-07-13T23:16:41.843508+00:00"
  },
  {
   "id": "2db1a85d-28a8-474d-907c-94dda1d2a32b",
   "presupuesto_id": "c9a33791-3d5b-4769-8179-2e4696b2e98e",
   "texto_original": "SOBREPASO 20 ACQUA",
   "texto_normalizado": "sobrepaso 20 acqua",
   "marca": null,
   "unidad": null,
   "cantidad": 6.0,
   "precio": 1298.45,
   "codigo_material": "INSTS125",
   "pendiente_id": null,
   "score_match": 100,
   "estado_match": "CONFIRMADO",
   "origen_match": "usuario",
   "created_at": "2026-07-13T23:16:41.843508+00:00"
  },
  {
   "id": "d8020c5f-dfd1-4f42-a839-747da72d791f",
   "presupuesto_id": "c9a33791-3d5b-4769-8179-2e4696b2e98e",
   "texto_original": "SOBREPASO 25 ACQUA",
   "texto_normalizado": "sobrepaso 25 acqua",
   "marca": null,
   "unidad": null,
   "cantidad": 2.0,
   "precio": 1955.23,
   "codigo_material": "INSTS126",
   "pendiente_id": null,
   "score_match": 100,
   "estado_match": "CONFIRMADO",
   "origen_match": "usuario",
   "created_at": "2026-07-13T23:16:41.843508+00:00"
  },
  {
   "id": "4dcdcd05-b6b9-4f59-870d-d82aed8d910e",
   "presupuesto_id": "c9a33791-3d5b-4769-8179-2e4696b2e98e",
   "texto_original": "CAÑO 160 MM AMANCO STD (900309)",
   "texto_normalizado": "caño 160 mm amanco std (900309)",
   "marca": null,
   "unidad": null,
   "cantidad": 1.0,
   "precio": 39572.8,
   "codigo_material": "INSTS019",
   "pendiente_id": null,
   "score_match": 90,
   "estado_match": "CONFIRMADO",
   "origen_match": "usuario",
   "created_at": "2026-07-13T23:16:41.843508+00:00"
  },
  {
   "id": "f454ec18-95c0-4f94-af33-4b26f21ff25e",
   "presupuesto_id": "c9a33791-3d5b-4769-8179-2e4696b2e98e",
   "texto_original": "CAMARA REGIS. DE LODOS 100 LTS (CR100) P/BIO AUTOLIMP.",
   "texto_normalizado": "camara regis. de lodos 100 lts (cr100) p/bio autolimp.",
   "marca": null,
   "unidad": null,
   "cantidad": 1.0,
   "precio": 74375.61,
   "codigo_material": "INSTS008",
   "pendiente_id": null,
   "score_match": 73,
   "estado_match": "CONFIRMADO",
   "origen_match": "usuario",
   "created_at": "2026-07-13T23:16:41.843508+00:00"
  },
  {
   "id": "084abec7-82c0-4c40-bd6c-0cfb80ad1465",
   "presupuesto_id": "c9a33791-3d5b-4769-8179-2e4696b2e98e",
   "texto_original": "CAÑO 1035 DE 110 X 4 AWA",
   "texto_normalizado": "caño 1035 de 110 x 4 awa",
   "marca": null,
   "unidad": null,
   "cantidad": 39.0,
   "precio": 21711.42,
   "codigo_material": "INSTS021",
   "pendiente_id": null,
   "score_match": 77,
   "estado_match": "CONFIRMADO",
   "origen_match": "usuario",
   "created_at": "2026-07-13T23:16:41.843508+00:00"
  },
  {
   "id": "e6234299-cb4a-4d83-9ba2-3de5e10fc4d6",
   "presupuesto_id": "c9a33791-3d5b-4769-8179-2e4696b2e98e",
   "texto_original": "CODO 2002 45 MH DE 50 AWA",
   "texto_normalizado": "codo 2002 45 mh de 50 awa",
   "marca": null,
   "unidad": null,
   "cantidad": 6.0,
   "precio": 808.5,
   "codigo_material": "INSTS036",
   "pendiente_id": null,
   "score_match": 78,
   "estado_match": "CONFIRMADO",
   "origen_match": "usuario",
   "created_at": "2026-07-13T23:16:41.843508+00:00"
  },
  {
   "id": "97c1b919-ee33-4b1d-b3d7-43a8ab8867a3",
   "presupuesto_id": "c9a33791-3d5b-4769-8179-2e4696b2e98e",
   "texto_original": "CODO 2003 45 MH DE 63 AWA",
   "texto_normalizado": "codo 2003 45 mh de 63 awa",
   "marca": null,
   "unidad": null,
   "cantidad": 6.0,
   "precio": 1356.79,
   "codigo_material": "INSTS037",
   "pendiente_id": null,
   "score_match": 84,
   "estado_match": "CONFIRMADO",
   "origen_match": "usuario",
   "created_at": "2026-07-13T23:16:41.843508+00:00"
  },
  {
   "id": "176a6b5b-20f9-444d-9dce-bc79b29da9f7",
   "presupuesto_id": "c9a33791-3d5b-4769-8179-2e4696b2e98e",
   "texto_original": "CODO 2004 45 MH DE 110 AWA",
   "texto_normalizado": "codo 2004 45 mh de 110 awa",
   "marca": null,
   "unidad": null,
   "cantidad": 5.0,
   "precio": 2917.0,
   "codigo_material": "INSTS038",
   "pendiente_id": null,
   "score_match": 81,
   "estado_match": "CONFIRMADO",
   "origen_match": "usuario",
   "created_at": "2026-07-13T23:16:41.843508+00:00"
  },
  {
   "id": "279c0ad2-d955-4842-9f25-4a2bd7c20710",
   "presupuesto_id": "c9a33791-3d5b-4769-8179-2e4696b2e98e",
   "texto_original": "CODO 2006 90 MH DE 50 AWA",
   "texto_normalizado": "codo 2006 90 mh de 50 awa",
   "marca": null,
   "unidad": null,
   "cantidad": 4.0,
   "precio": 808.5,
   "codigo_material": "INSTS040",
   "pendiente_id": null,
   "score_match": 72,
   "estado_match": "CONFIRMADO",
   "origen_match": "usuario",
   "created_at": "2026-07-13T23:16:41.843508+00:00"
  },
  {
   "id": "68a3f8fd-ea74-4dce-b194-4daeb0173e9b",
   "presupuesto_id": "c9a33791-3d5b-4769-8179-2e4696b2e98e",
   "texto_original": "MANGUITO 2016 DE REP. HH DE 110 AWA",
   "texto_normalizado": "manguito 2016 de rep. hh de 110 awa",
   "marca": null,
   "unidad": null,
   "cantidad": 20.0,
   "precio": 3018.18,
   "codigo_material": "INSTS052",
   "pendiente_id": null,
   "score_match": 63,
   "estado_match": "CONFIRMADO",
   "origen_match": "usuario",
   "created_at": "2026-07-13T23:16:41.843508+00:00"
  },
  {
   "id": "99b42290-8a96-49e0-8c8d-0b72dafa70b4",
   "presupuesto_id": "c9a33791-3d5b-4769-8179-2e4696b2e98e",
   "texto_original": "SOLUCION 4022 DESLIZ 400 CC AWA",
   "texto_normalizado": "solucion 4022 desliz 400 cc awa",
   "marca": null,
   "unidad": null,
   "cantidad": 1.0,
   "precio": 10442.32,
   "codigo_material": "INSTS069",
   "pendiente_id": null,
   "score_match": 62,
   "estado_match": "CONFIRMADO",
   "origen_match": "usuario",
   "created_at": "2026-07-13T23:16:41.843508+00:00"
  },
  {
   "id": "ea957c8f-8e37-4b39-9a88-d31c4fb28c67",
   "presupuesto_id": "c9a33791-3d5b-4769-8179-2e4696b2e98e",
   "texto_original": "CAÑO 32MM MAGNUM PN20 A/FRIA YCAL",
   "texto_normalizado": "caño 32mm magnum pn20 a/fria ycal",
   "marca": null,
   "unidad": null,
   "cantidad": 8.0,
   "precio": 15191.16,
   "codigo_material": "INSTS076",
   "pendiente_id": null,
   "score_match": 66,
   "estado_match": "CONFIRMADO",
   "origen_match": "usuario",
   "created_at": "2026-07-13T23:16:41.843508+00:00"
  },
  {
   "id": "707ad3b4-6c46-4d42-8972-0a7deef2e004",
   "presupuesto_id": "c9a33791-3d5b-4769-8179-2e4696b2e98e",
   "texto_original": "CAÑO 50MM MAGNUM PN20 A/FRIA YCAL",
   "texto_normalizado": "caño 50mm magnum pn20 a/fria ycal",
   "marca": null,
   "unidad": null,
   "cantidad": 3.0,
   "precio": 33394.73,
   "codigo_material": "INSTS077",
   "pendiente_id": null,
   "score_match": 66,
   "estado_match": "CONFIRMADO",
   "origen_match": "usuario",
   "created_at": "2026-07-13T23:16:41.843508+00:00"
  },
  {
   "id": "f893141f-3d6f-498e-b3d0-c9072c1ab157",
   "presupuesto_id": "c9a33791-3d5b-4769-8179-2e4696b2e98e",
   "texto_original": "TEE RED.CENT. 25-20-25 ACQUA",
   "texto_normalizado": "tee red.cent. 25-20-25 acqua",
   "marca": null,
   "unidad": null,
   "cantidad": 2.0,
   "precio": 1040.42,
   "codigo_material": "INSTS099",
   "pendiente_id": null,
   "score_match": 70,
   "estado_match": "CONFIRMADO",
   "origen_match": "usuario",
   "created_at": "2026-07-13T23:16:41.843508+00:00"
  },
  {
   "id": "008e763a-2f33-4d81-b72b-d070e11ecba8",
   "presupuesto_id": "c9a33791-3d5b-4769-8179-2e4696b2e98e",
   "texto_original": "CAÑO 20MM MAGNUM PN20 A/FRIA YCAL",
   "texto_normalizado": "caño 20mm magnum pn20 a/fria ycal",
   "marca": null,
   "unidad": null,
   "cantidad": 6.0,
   "precio": 6716.72,
   "codigo_material": "INSTS172",
   "pendiente_id": "1f652f6e-5638-445b-b66b-bda30d5cfea0",
   "score_match": 66,
   "estado_match": "REVISAR",
   "origen_match": "fuzzy",
   "created_at": "2026-07-13T23:16:41.843508+00:00"
  },
  {
   "id": "8db33113-660c-413c-a081-e32b01a794c3",
   "presupuesto_id": "c9a33791-3d5b-4769-8179-2e4696b2e98e",
   "texto_original": "REJA 15 X 15 A/INOX MARCO FUND C/EMB (COD 503)",
   "texto_normalizado": "reja 15 x 15 a/inox marco fund c/emb (cod 503)",
   "marca": null,
   "unidad": null,
   "cantidad": 3.0,
   "precio": 11017.63,
   "codigo_material": "INSTS008",
   "pendiente_id": "a19ac084-7392-4ed2-bae4-f6802ed3cf9d",
   "score_match": 83,
   "estado_match": "REVISAR",
   "origen_match": "fuzzy",
   "created_at": "2026-07-13T23:16:41.843508+00:00"
  },
  {
   "id": "51da6353-04b8-46d7-892b-b69766cf1a11",
   "presupuesto_id": "836af4a1-ec4e-4079-bfbf-7ce6a1ff8374",
   "texto_original": "CODO MH 110X90 DURATOP",
   "texto_normalizado": "codo mh 110x90 duratop",
   "marca": null,
   "unidad": null,
   "cantidad": 8.0,
   "precio": 2806.97,
   "codigo_material": "INSTS036",
   "pendiente_id": null,
   "score_match": 87,
   "estado_match": "CONFIRMADO",
   "origen_match": "usuario",
   "created_at": "2026-07-13T23:16:39.56214+00:00"
  },
  {
   "id": "7813a8b9-024b-454b-9b96-927f4ab6219e",
   "presupuesto_id": "836af4a1-ec4e-4079-bfbf-7ce6a1ff8374",
   "texto_original": "MANGUITO REPARACION 50 DURATOP",
   "texto_normalizado": "manguito reparacion 50 duratop",
   "marca": null,
   "unidad": null,
   "cantidad": 6.0,
   "precio": 1204.71,
   "codigo_material": "INSTS054",
   "pendiente_id": null,
   "score_match": 78,
   "estado_match": "CONFIRMADO",
   "origen_match": "usuario",
   "created_at": "2026-07-13T23:16:39.56214+00:00"
  },
  {
   "id": "2b646fd1-4423-4576-af86-416d9a6665b5",
   "presupuesto_id": "836af4a1-ec4e-4079-bfbf-7ce6a1ff8374",
   "texto_original": "A.SYSTEM CANO PN20 CALIENTE 32X4 M",
   "texto_normalizado": "a.system cano pn20 caliente 32x4 m",
   "marca": null,
   "unidad": null,
   "cantidad": 8.0,
   "precio": 12816.73,
   "codigo_material": "INSTS076",
   "pendiente_id": null,
   "score_match": 75,
   "estado_match": "CONFIRMADO",
   "origen_match": "usuario",
   "created_at": "2026-07-13T23:16:39.56214+00:00"
  },
  {
   "id": "855c5bd0-66e5-4f8e-8970-75f799d43682",
   "presupuesto_id": "c9a33791-3d5b-4769-8179-2e4696b2e98e",
   "texto_original": "CAMARA DESENGRASADORA 110*110 (CD110)",
   "texto_normalizado": "camara desengrasadora 110*110 (cd110)",
   "marca": null,
   "unidad": null,
   "cantidad": 1.0,
   "precio": 47247.43,
   "codigo_material": "INSTS004",
   "pendiente_id": null,
   "score_match": 88,
   "estado_match": "CONFIRMADO",
   "origen_match": "usuario",
   "created_at": "2026-07-13T23:16:41.843508+00:00"
  },
  {
   "id": "6056dcbb-5577-4385-8c76-a8b9d08b4d97",
   "presupuesto_id": "c9a33791-3d5b-4769-8179-2e4696b2e98e",
   "texto_original": "UNION DOBLE MIXTA RH 50 X 11/2 ACQUA",
   "texto_normalizado": "union doble mixta rh 50 x 11/2 acqua",
   "marca": null,
   "unidad": null,
   "cantidad": 2.0,
   "precio": 42485.75,
   "codigo_material": "INSTS054",
   "pendiente_id": null,
   "score_match": 100,
   "estado_match": "CONFIRMADO",
   "origen_match": "usuario",
   "created_at": "2026-07-13T23:16:41.843508+00:00"
  },
  {
   "id": "9ea9b511-ff97-44e9-9607-4815b9666bac",
   "presupuesto_id": "c9a33791-3d5b-4769-8179-2e4696b2e98e",
   "texto_original": "CAMARA INSP PVC TUBOFORTE",
   "texto_normalizado": "camara insp pvc tuboforte",
   "marca": null,
   "unidad": null,
   "cantidad": 1.0,
   "precio": 43047.29,
   "codigo_material": "INSTS005",
   "pendiente_id": null,
   "score_match": 62,
   "estado_match": "CONFIRMADO",
   "origen_match": "usuario",
   "created_at": "2026-07-13T23:16:41.843508+00:00"
  },
  {
   "id": "16267677-3e79-43e5-a8cf-664a16db8308",
   "presupuesto_id": "c9a33791-3d5b-4769-8179-2e4696b2e98e",
   "texto_original": "PILETA 2053 PATIO 3 ENT C/SIFON DES AWA",
   "texto_normalizado": "pileta 2053 patio 3 ent c/sifon des awa",
   "marca": null,
   "unidad": null,
   "cantidad": 2.0,
   "precio": 7012.14,
   "codigo_material": "INSTS056",
   "pendiente_id": null,
   "score_match": 80,
   "estado_match": "CONFIRMADO",
   "origen_match": "usuario",
   "created_at": "2026-07-13T23:16:41.843508+00:00"
  },
  {
   "id": "092c5145-4441-4e91-ae48-9b74e2413c3f",
   "presupuesto_id": "836af4a1-ec4e-4079-bfbf-7ce6a1ff8374",
   "texto_original": "CANO DURATOP 63X2.00 MTS",
   "texto_normalizado": "cano duratop 63x2.00 mts",
   "marca": null,
   "unidad": null,
   "cantidad": 2.0,
   "precio": 5833.76,
   "codigo_material": "INSTS053",
   "pendiente_id": "50013dec-2f1d-42f1-930a-7ac8822529f3",
   "score_match": 78,
   "estado_match": "REVISAR",
   "origen_match": "fuzzy",
   "created_at": "2026-07-13T23:16:39.56214+00:00"
  },
  {
   "id": "353ac488-ab26-4be3-8314-6834399df64b",
   "presupuesto_id": "abd5f0b1-cd6c-4da1-9a0e-40c7adfca23b",
   "texto_original": "PASTINA X1KG",
   "texto_normalizado": "pastina x1kg",
   "marca": null,
   "unidad": null,
   "cantidad": 60.0,
   "precio": 2000.66,
   "codigo_material": "CONS104",
   "pendiente_id": null,
   "score_match": 100,
   "estado_match": "CONFIRMADO",
   "origen_match": "usuario",
   "created_at": "2026-07-13T23:41:05.015722+00:00"
  },
  {
   "id": "f51e257d-6b51-41c9-88ac-d2d135b5ccf5",
   "presupuesto_id": "abd5f0b1-cd6c-4da1-9a0e-40c7adfca23b",
   "texto_original": "ARENA BOLSON",
   "texto_normalizado": "arena bolson",
   "marca": null,
   "unidad": null,
   "cantidad": 23.0,
   "precio": 47000.34,
   "codigo_material": "CONS108",
   "pendiente_id": null,
   "score_match": 100,
   "estado_match": "CONFIRMADO",
   "origen_match": "usuario",
   "created_at": "2026-07-13T23:41:05.015722+00:00"
  },
  {
   "id": "cad18520-c597-4aea-91e4-b9989dc25d40",
   "presupuesto_id": "abd5f0b1-cd6c-4da1-9a0e-40c7adfca23b",
   "texto_original": "LADRILLO REF 229X114X50",
   "texto_normalizado": "ladrillo ref 229x114x50",
   "marca": null,
   "unidad": null,
   "cantidad": 208.0,
   "precio": 4569.57,
   "codigo_material": "CONS125",
   "pendiente_id": null,
   "score_match": 100,
   "estado_match": "CONFIRMADO",
   "origen_match": "usuario",
   "created_at": "2026-07-13T23:41:05.015722+00:00"
  },
  {
   "id": "4c70f901-6065-4f0b-9056-f6f210938c04",
   "presupuesto_id": "abd5f0b1-cd6c-4da1-9a0e-40c7adfca23b",
   "texto_original": "VARILLA 6",
   "texto_normalizado": "varilla 6",
   "marca": null,
   "unidad": null,
   "cantidad": 107.0,
   "precio": 6700.73,
   "codigo_material": "A006",
   "pendiente_id": "0cd14d5d-9687-42be-95e8-04fe10e28ba4",
   "score_match": 84,
   "estado_match": "REVISAR",
   "origen_match": "fuzzy",
   "created_at": "2026-07-13T23:41:05.015722+00:00"
  },
  {
   "id": "e2ed9be6-8dd7-4768-94a4-26aa4bba6205",
   "presupuesto_id": "abd5f0b1-cd6c-4da1-9a0e-40c7adfca23b",
   "texto_original": "VARILLA 12",
   "texto_normalizado": "varilla 12",
   "marca": null,
   "unidad": null,
   "cantidad": 8.0,
   "precio": 26000.0,
   "codigo_material": "A006",
   "pendiente_id": "646e923a-3c7a-4898-9e4f-a6b96cc42c60",
   "score_match": 84,
   "estado_match": "REVISAR",
   "origen_match": "fuzzy",
   "created_at": "2026-07-13T23:41:05.015722+00:00"
  },
  {
   "id": "60d1e3b5-2418-4f49-8d97-3a1674765f2b",
   "presupuesto_id": "abd5f0b1-cd6c-4da1-9a0e-40c7adfca23b",
   "texto_original": "VARILLA 8",
   "texto_normalizado": "varilla 8",
   "marca": null,
   "unidad": null,
   "cantidad": 58.0,
   "precio": 11800.13,
   "codigo_material": "A006",
   "pendiente_id": "4e20e005-7a1b-4f48-9ac2-f92cfa67e129",
   "score_match": 84,
   "estado_match": "REVISAR",
   "origen_match": "fuzzy",
   "created_at": "2026-07-13T23:41:05.015722+00:00"
  },
  {
   "id": "3fb0d605-e4d9-456f-ba08-aa2ee77f88ce",
   "presupuesto_id": "c4fc4453-61d5-446d-aac1-cceca3e4cf2b",
   "texto_original": "PASTINA WEBER CLASSIC X 5KG COLOR",
   "texto_normalizado": "pastina weber classic x 5kg color",
   "marca": null,
   "unidad": null,
   "cantidad": 12.0,
   "precio": 11312.22,
   "codigo_material": "CONS104",
   "pendiente_id": null,
   "score_match": 100,
   "estado_match": "CONFIRMADO",
   "origen_match": "usuario",
   "created_at": "2026-07-14T00:46:33.684124+00:00"
  },
  {
   "id": "8ee193b3-1d94-41b6-867f-194f302f0165",
   "presupuesto_id": "c4fc4453-61d5-446d-aac1-cceca3e4cf2b",
   "texto_original": "HIERRO 12 MM",
   "texto_normalizado": "hierro 12 mm",
   "marca": null,
   "unidad": null,
   "cantidad": 8.0,
   "precio": 21900.45,
   "codigo_material": "A006",
   "pendiente_id": null,
   "score_match": 100,
   "estado_match": "CONFIRMADO",
   "origen_match": "usuario",
   "created_at": "2026-07-14T00:46:33.684124+00:00"
  },
  {
   "id": "a49500a5-1749-40b6-aa8b-567b5822c71a",
   "presupuesto_id": "b606c5b4-3b5e-4cad-9f06-72f587fbb524",
   "texto_original": "VARILLA GALV P/ANCLAJE W1/2\"X1000MM",
   "texto_normalizado": "varilla galv p/anclaje w1/2\"x1000mm",
   "marca": null,
   "unidad": null,
   "cantidad": 1.0,
   "precio": 11792.57,
   "codigo_material": "A006",
   "pendiente_id": null,
   "score_match": 100,
   "estado_match": "CONFIRMADO",
   "origen_match": "usuario",
   "created_at": "2026-07-14T00:43:15.407+00:00"
  },
  {
   "id": "f1bf01ec-3c14-42d8-9f6e-2c62a9ceae69",
   "presupuesto_id": "b606c5b4-3b5e-4cad-9f06-72f587fbb524",
   "texto_original": "FLEJE CRUZ SAN ANDRES GALV C18 Des.35-60mm",
   "texto_normalizado": "fleje cruz san andres galv c18 des.35-60mm",
   "marca": null,
   "unidad": null,
   "cantidad": 1.0,
   "precio": 3440787.48,
   "codigo_material": "A001",
   "pendiente_id": "d5e88b64-d741-4cc6-b9f8-dab4ea6c550d",
   "score_match": 100,
   "estado_match": "REVISAR",
   "origen_match": "fuzzy",
   "created_at": "2026-07-14T00:43:15.407+00:00"
  },
  {
   "id": "8c78630c-11a0-4eed-a181-d88a86a90455",
   "presupuesto_id": "f073b605-d5d8-428a-9c3d-fe9d30ffc04d",
   "texto_original": "CRUZ DE SAN ANDRÉS 50 MM (X50M) 0,94 MM",
   "texto_normalizado": "cruz de san andrés 50 mm (x50m) 0,94 mm",
   "marca": null,
   "unidad": null,
   "cantidad": 9.0,
   "precio": 69052.24,
   "codigo_material": "A001",
   "pendiente_id": null,
   "score_match": 91,
   "estado_match": "CONFIRMADO",
   "origen_match": "usuario",
   "created_at": "2026-07-14T00:46:32.666314+00:00"
  },
  {
   "id": "88c795b2-eabd-4f89-9c06-cc1ef1074bf9",
   "presupuesto_id": "290caab4-ee21-4c20-a829-970345df6f1d",
   "texto_original": "ARENA NECO BOLSON X 1.2TN",
   "texto_normalizado": "arena neco bolson x 1.2tn",
   "marca": null,
   "unidad": null,
   "cantidad": 23.0,
   "precio": 40316.74,
   "codigo_material": "CONS108",
   "pendiente_id": null,
   "score_match": 89,
   "estado_match": "CONFIRMADO",
   "origen_match": "usuario",
   "created_at": "2026-07-14T01:00:35.919053+00:00"
  },
  {
   "id": "8ea3361f-d18b-401b-b12f-1cee1f88d655",
   "presupuesto_id": "f2c3bfb4-a079-4fd7-8233-f726eb74588d",
   "texto_original": "ARENA AMARILLA X 1 BIG BAG",
   "texto_normalizado": "arena amarilla x 1 big bag",
   "marca": null,
   "unidad": null,
   "cantidad": 23.0,
   "precio": 48933.76,
   "codigo_material": "CONS108",
   "pendiente_id": null,
   "score_match": 100,
   "estado_match": "MATCH",
   "origen_match": "fuzzy",
   "created_at": "2026-07-22T15:26:09.526663+00:00"
  },
  {
   "id": "1db1ae3c-5735-4b6f-bb2d-8b615f4b2b18",
   "presupuesto_id": "fe5803f5-f2db-4ed2-8205-470b4aa26dff",
   "texto_original": "HIERRO 12.00 MM",
   "texto_normalizado": "hierro 12.00 mm",
   "marca": null,
   "unidad": null,
   "cantidad": 8.0,
   "precio": 20654.39,
   "codigo_material": "A006",
   "pendiente_id": null,
   "score_match": 100,
   "estado_match": "CONFIRMADO",
   "origen_match": "usuario",
   "created_at": "2026-07-14T01:00:50.469391+00:00"
  },
  {
   "id": "7747fe1e-bf81-4ebe-94e5-a255cff80833",
   "presupuesto_id": "290caab4-ee21-4c20-a829-970345df6f1d",
   "texto_original": "PEDREG. 3-1 BOLSON X 1.2 TN",
   "texto_normalizado": "pedreg. 3-1 bolson x 1.2 tn",
   "marca": null,
   "unidad": null,
   "cantidad": 18.0,
   "precio": 54081.45,
   "codigo_material": "CONS108",
   "pendiente_id": "39d760c2-372e-48a5-8d23-1adce8a6e581",
   "score_match": 67,
   "estado_match": "REVISAR",
   "origen_match": "fuzzy",
   "created_at": "2026-07-14T01:00:35.919053+00:00"
  },
  {
   "id": "9ffe555e-594b-448e-b998-71f547dcb936",
   "presupuesto_id": "f2c3bfb4-a079-4fd7-8233-f726eb74588d",
   "texto_original": "FARA REFRACTARIO RECTO 229X114X63MM 6CM",
   "texto_normalizado": "fara refractario recto 229x114x63mm 6cm",
   "marca": null,
   "unidad": null,
   "cantidad": 208.0,
   "precio": 4501.13,
   "codigo_material": "CONS125",
   "pendiente_id": null,
   "score_match": 74,
   "estado_match": "REVISAR",
   "origen_match": "fuzzy",
   "created_at": "2026-07-22T15:26:09.526663+00:00"
  },
  {
   "id": "7ff5aac2-ca4a-49cd-b734-7a3c78cb2f0e",
   "presupuesto_id": "54c44c3f-183c-4f85-a852-fa01c003f594",
   "texto_original": "HIERRO 12 MM ACINDAR/BRAGADO",
   "texto_normalizado": "hierro 12 mm acindar/bragado",
   "marca": null,
   "unidad": null,
   "cantidad": 8.0,
   "precio": 17332.51,
   "codigo_material": "A006",
   "pendiente_id": null,
   "score_match": 100,
   "estado_match": "MATCH",
   "origen_match": "fuzzy",
   "created_at": "2026-07-22T15:26:11.014334+00:00"
  },
  {
   "id": "82964e06-6720-4ff3-abb0-04f1419c2b6f",
   "presupuesto_id": "54c44c3f-183c-4f85-a852-fa01c003f594",
   "texto_original": "REF LAD RECTO 229X114X63 ART 1",
   "texto_normalizado": "ref lad recto 229x114x63 art 1",
   "marca": null,
   "unidad": null,
   "cantidad": 208.0,
   "precio": 4065.03,
   "codigo_material": "CONS125",
   "pendiente_id": null,
   "score_match": 100,
   "estado_match": "MATCH",
   "origen_match": "fuzzy",
   "created_at": "2026-07-22T15:26:11.014334+00:00"
  },
  {
   "id": "1f3902d3-4183-4cd3-97da-8d49983d2e01",
   "presupuesto_id": "ce3a5ba0-68e0-4d94-a8c6-e990728f66d3",
   "texto_original": "VARILLA ROSCADA 12 X 160 ( FISCHER)",
   "texto_normalizado": "varilla roscada 12 x 160 ( fischer)",
   "marca": null,
   "unidad": null,
   "cantidad": 52.0,
   "precio": 3358.99,
   "codigo_material": "A006",
   "pendiente_id": null,
   "score_match": 100,
   "estado_match": "CONFIRMADO",
   "origen_match": "usuario",
   "created_at": "2026-07-14T01:41:30.295985+00:00"
  },
  {
   "id": "e3714cba-3da5-4a43-bbab-a53b9f18e307",
   "presupuesto_id": "ce3a5ba0-68e0-4d94-a8c6-e990728f66d3",
   "texto_original": "MONTANTE DE 34 X 2.60 MTS (BARBIERI)",
   "texto_normalizado": "montante de 34 x 2.60 mts (barbieri)",
   "marca": null,
   "unidad": null,
   "cantidad": 426.0,
   "precio": 3236.02,
   "codigo_material": "HIE001",
   "pendiente_id": null,
   "score_match": 93,
   "estado_match": "CONFIRMADO",
   "origen_match": "usuario",
   "created_at": "2026-07-14T01:41:30.295985+00:00"
  },
  {
   "id": "072c1719-6a8c-43af-ada6-7ca7bfde23ef",
   "presupuesto_id": "ce3a5ba0-68e0-4d94-a8c6-e990728f66d3",
   "texto_original": "JUNTA DILATACION PVC X 3 MTS (BARBIERI)",
   "texto_normalizado": "junta dilatacion pvc x 3 mts (barbieri)",
   "marca": null,
   "unidad": null,
   "cantidad": 2.0,
   "precio": 4470.25,
   "codigo_material": "HIE001",
   "pendiente_id": null,
   "score_match": 100,
   "estado_match": "CONFIRMADO",
   "origen_match": "usuario",
   "created_at": "2026-07-14T01:41:30.295985+00:00"
  },
  {
   "id": "ec51c1b0-be7f-4ae1-8f48-f7ac25e956ee",
   "presupuesto_id": "ce3a5ba0-68e0-4d94-a8c6-e990728f66d3",
   "texto_original": "FLEJE S-A X 50 MTS ESP 0.5 (B) (BARBIERI)",
   "texto_normalizado": "fleje s-a x 50 mts esp 0.5 (b) (barbieri)",
   "marca": null,
   "unidad": null,
   "cantidad": 9.0,
   "precio": 38914.46,
   "codigo_material": "A001",
   "pendiente_id": null,
   "score_match": 70,
   "estado_match": "CONFIRMADO",
   "origen_match": "usuario",
   "created_at": "2026-07-14T01:41:30.295985+00:00"
  },
  {
   "id": "604805d2-3f78-4bbc-b8cd-5a05ce09601c",
   "presupuesto_id": "ce3a5ba0-68e0-4d94-a8c6-e990728f66d3",
   "texto_original": "LANA R400 70 MM - 0.40 X 13 - 15,60 M2 (ISOVER)",
   "texto_normalizado": "lana r400 70 mm - 0.40 x 13 - 15,60 m2 (isover)",
   "marca": null,
   "unidad": null,
   "cantidad": 8.0,
   "precio": 109301.95,
   "codigo_material": "AISL113",
   "pendiente_id": null,
   "score_match": 81,
   "estado_match": "CONFIRMADO",
   "origen_match": "usuario",
   "created_at": "2026-07-14T01:41:30.295985+00:00"
  },
  {
   "id": "120b1fc1-dc7c-414e-8bbb-35bbc65157c5",
   "presupuesto_id": "0a5e78a7-e65e-4bfe-97cb-19132da30a71",
   "texto_original": "PRESURIZADOR TANGO SFL 20 ROWA",
   "texto_normalizado": "presurizador tango sfl 20 rowa",
   "marca": null,
   "unidad": null,
   "cantidad": 1.0,
   "precio": 388418.3,
   "codigo_material": "INSTS016",
   "pendiente_id": null,
   "score_match": 100,
   "estado_match": "MATCH",
   "origen_match": "fuzzy",
   "created_at": "2026-07-14T11:28:56.286309+00:00"
  },
  {
   "id": "c628c64e-e7a9-428d-a65a-7aa1d8df77f0",
   "presupuesto_id": "0a5e78a7-e65e-4bfe-97cb-19132da30a71",
   "texto_original": "UNION SIMPLE FUSION 32 MM 22325035 TIGRE",
   "texto_normalizado": "union simple fusion 32 mm 22325035 tigre",
   "marca": null,
   "unidad": null,
   "cantidad": 15.0,
   "precio": 370.64,
   "codigo_material": "INSTS123",
   "pendiente_id": null,
   "score_match": 90,
   "estado_match": "MATCH",
   "origen_match": "fuzzy",
   "created_at": "2026-07-14T11:28:56.286309+00:00"
  },
  {
   "id": "832b7048-68c6-4909-9c66-a6a5b073a1f7",
   "presupuesto_id": "0a5e78a7-e65e-4bfe-97cb-19132da30a71",
   "texto_original": "UNION SIMPLE FUSION 50 MM 22325051 TIGRE",
   "texto_normalizado": "union simple fusion 50 mm 22325051 tigre",
   "marca": null,
   "unidad": null,
   "cantidad": 1.0,
   "precio": 1305.49,
   "codigo_material": "INSTS054",
   "pendiente_id": null,
   "score_match": 100,
   "estado_match": "MATCH",
   "origen_match": "fuzzy",
   "created_at": "2026-07-14T11:28:56.286309+00:00"
  },
  {
   "id": "f0b5fb92-f97d-4f76-979c-955243429007",
   "presupuesto_id": "0a5e78a7-e65e-4bfe-97cb-19132da30a71",
   "texto_original": "REJA MARCO DE ACERO 15X15 RMA1515 WATERPLAST",
   "texto_normalizado": "reja marco de acero 15x15 rma1515 waterplast",
   "marca": null,
   "unidad": null,
   "cantidad": 4.0,
   "precio": 4922.67,
   "codigo_material": "INSTS008",
   "pendiente_id": null,
   "score_match": 100,
   "estado_match": "MATCH",
   "origen_match": "fuzzy",
   "created_at": "2026-07-14T11:28:56.286309+00:00"
  },
  {
   "id": "3c204569-6890-4446-ac5e-7752887bf309",
   "presupuesto_id": "0a5e78a7-e65e-4bfe-97cb-19132da30a71",
   "texto_original": "MARCO BRONCE C/TAPA ACERO INOX 15X15 DURATOP",
   "texto_normalizado": "marco bronce c/tapa acero inox 15x15 duratop",
   "marca": null,
   "unidad": null,
   "cantidad": 3.0,
   "precio": 6278.91,
   "codigo_material": "INSTS008",
   "pendiente_id": null,
   "score_match": 86,
   "estado_match": "MATCH",
   "origen_match": "fuzzy",
   "created_at": "2026-07-14T11:28:56.286309+00:00"
  },
  {
   "id": "38071669-4bfa-46e8-a93d-de8565738c74",
   "presupuesto_id": "0a5e78a7-e65e-4bfe-97cb-19132da30a71",
   "texto_original": "CUPLA PVC SOLDABLE 50 22406280 TIGRE",
   "texto_normalizado": "cupla pvc soldable 50 22406280 tigre",
   "marca": null,
   "unidad": null,
   "cantidad": 24.0,
   "precio": 855.84,
   "codigo_material": "INSTS054",
   "pendiente_id": null,
   "score_match": 100,
   "estado_match": "MATCH",
   "origen_match": "fuzzy",
   "created_at": "2026-07-14T11:28:56.286309+00:00"
  },
  {
   "id": "9ef99434-321b-40f6-882d-b5b2807fa048",
   "presupuesto_id": "0a5e78a7-e65e-4bfe-97cb-19132da30a71",
   "texto_original": "DESAGUE AQUA LINEAL 70CM CLAS.BRIL ATRIM",
   "texto_normalizado": "desague aqua lineal 70cm clas.bril atrim",
   "marca": null,
   "unidad": null,
   "cantidad": 3.0,
   "precio": 113465.29,
   "codigo_material": "INSTS009",
   "pendiente_id": null,
   "score_match": 76,
   "estado_match": "REVISAR",
   "origen_match": "fuzzy",
   "created_at": "2026-07-14T11:28:56.286309+00:00"
  },
  {
   "id": "1110563f-fb87-49dd-a5fa-5326f200f07f",
   "presupuesto_id": "0a5e78a7-e65e-4bfe-97cb-19132da30a71",
   "texto_original": "TUBO PPR3-PN 20 20MM IRAM 17010018 TIGRE",
   "texto_normalizado": "tubo ppr3-pn 20 20mm iram 17010018 tigre",
   "marca": null,
   "unidad": null,
   "cantidad": 19.0,
   "precio": 3268.01,
   "codigo_material": "INSTE077",
   "pendiente_id": null,
   "score_match": 83,
   "estado_match": "REVISAR",
   "origen_match": "fuzzy",
   "created_at": "2026-07-14T11:28:56.286309+00:00"
  },
  {
   "id": "9cc618d8-aad5-4db1-83b8-25404b39c657",
   "presupuesto_id": "0a5e78a7-e65e-4bfe-97cb-19132da30a71",
   "texto_original": "TUBO PPR3-PN 20 25MM IRAM 17010034 TIGRE",
   "texto_normalizado": "tubo ppr3-pn 20 25mm iram 17010034 tigre",
   "marca": null,
   "unidad": null,
   "cantidad": 36.0,
   "precio": 4743.75,
   "codigo_material": "INSTE077",
   "pendiente_id": null,
   "score_match": 83,
   "estado_match": "REVISAR",
   "origen_match": "fuzzy",
   "created_at": "2026-07-14T11:28:56.286309+00:00"
  },
  {
   "id": "2da8bc84-b00d-48eb-9f9f-95a08bb190cb",
   "presupuesto_id": "0a5e78a7-e65e-4bfe-97cb-19132da30a71",
   "texto_original": "TUBO PPR3-PN 20 32MM IRAM 17010050 TIGRE",
   "texto_normalizado": "tubo ppr3-pn 20 32mm iram 17010050 tigre",
   "marca": null,
   "unidad": null,
   "cantidad": 24.0,
   "precio": 7377.19,
   "codigo_material": "INSTE077",
   "pendiente_id": null,
   "score_match": 83,
   "estado_match": "REVISAR",
   "origen_match": "fuzzy",
   "created_at": "2026-07-14T11:28:56.286309+00:00"
  },
  {
   "id": "71022403-4a11-433c-8b67-a3ff2fcfc736",
   "presupuesto_id": "0a5e78a7-e65e-4bfe-97cb-19132da30a71",
   "texto_original": "TUBO PPR3-PN 20 50MM IRAM 17010093 TIGRE",
   "texto_normalizado": "tubo ppr3-pn 20 50mm iram 17010093 tigre",
   "marca": null,
   "unidad": null,
   "cantidad": 6.0,
   "precio": 19755.38,
   "codigo_material": "INSTE077",
   "pendiente_id": null,
   "score_match": 83,
   "estado_match": "REVISAR",
   "origen_match": "fuzzy",
   "created_at": "2026-07-14T11:28:56.286309+00:00"
  },
  {
   "id": "4cbaf0f7-df4d-4d49-b8ac-382f8606d785",
   "presupuesto_id": "0a5e78a7-e65e-4bfe-97cb-19132da30a71",
   "texto_original": "TE NORMAL FUSION 20X20X20 22322508 TIGRE",
   "texto_normalizado": "te normal fusion 20x20x20 22322508 tigre",
   "marca": null,
   "unidad": null,
   "cantidad": 8.0,
   "precio": 259.77,
   "codigo_material": "INSTS093",
   "pendiente_id": null,
   "score_match": 76,
   "estado_match": "REVISAR",
   "origen_match": "fuzzy",
   "created_at": "2026-07-14T11:28:56.286309+00:00"
  },
  {
   "id": "43e6723a-c16d-440f-b93a-ffe937f768a8",
   "presupuesto_id": "0a5e78a7-e65e-4bfe-97cb-19132da30a71",
   "texto_original": "REJA C/MARCO FUNDIDO LINEA PRO 15X15 WATERPLAST",
   "texto_normalizado": "reja c/marco fundido linea pro 15x15 waterplast",
   "marca": null,
   "unidad": null,
   "cantidad": 2.0,
   "precio": 10444.05,
   "codigo_material": "INSTS008",
   "pendiente_id": null,
   "score_match": 77,
   "estado_match": "REVISAR",
   "origen_match": "fuzzy",
   "created_at": "2026-07-14T11:28:56.286309+00:00"
  },
  {
   "id": "38ce751c-98db-498b-9c93-84672b97e83f",
   "presupuesto_id": "0a5e78a7-e65e-4bfe-97cb-19132da30a71",
   "texto_original": "CAÑO SOLDABLE PVC 50X2.4X6M CL.10 JP TIGRE",
   "texto_normalizado": "caño soldable pvc 50x2.4x6m cl.10 jp tigre",
   "marca": null,
   "unidad": null,
   "cantidad": 40.0,
   "precio": 20220.51,
   "codigo_material": "INSTE077",
   "pendiente_id": null,
   "score_match": 73,
   "estado_match": "REVISAR",
   "origen_match": "fuzzy",
   "created_at": "2026-07-14T11:28:56.286309+00:00"
  },
  {
   "id": "1be964af-528e-4229-ade3-543875962f32",
   "presupuesto_id": "0a5e78a7-e65e-4bfe-97cb-19132da30a71",
   "texto_original": "CAJA MEDIDOR DE AGUA DOM 40X20X18 CM WATERPLAST",
   "texto_normalizado": "caja medidor de agua dom 40x20x18 cm waterplast",
   "marca": null,
   "unidad": null,
   "cantidad": 7.0,
   "precio": 10643.62,
   "codigo_material": "INSTS008",
   "pendiente_id": null,
   "score_match": 73,
   "estado_match": "REVISAR",
   "origen_match": "fuzzy",
   "created_at": "2026-07-14T11:28:56.286309+00:00"
  },
  {
   "id": "81fd8613-1519-4c56-a21c-605822f1b174",
   "presupuesto_id": "ee48cb06-b8cc-4c95-ad47-24a5d9fdfd36",
   "texto_original": "PRESURIZADOR TANGO SFL 20 ROWA",
   "texto_normalizado": "presurizador tango sfl 20 rowa",
   "marca": null,
   "unidad": null,
   "cantidad": 1.0,
   "precio": 388418.3,
   "codigo_material": "INSTS016",
   "pendiente_id": null,
   "score_match": 100,
   "estado_match": "MATCH",
   "origen_match": "fuzzy",
   "created_at": "2026-07-14T11:28:58.064449+00:00"
  },
  {
   "id": "d2866abf-1ae3-4380-987d-e6edcb5798a3",
   "presupuesto_id": "ee48cb06-b8cc-4c95-ad47-24a5d9fdfd36",
   "texto_original": "UNION SIMPLE FUSION 32 MM 22325035 TIGRE",
   "texto_normalizado": "union simple fusion 32 mm 22325035 tigre",
   "marca": null,
   "unidad": null,
   "cantidad": 15.0,
   "precio": 370.64,
   "codigo_material": "INSTS123",
   "pendiente_id": null,
   "score_match": 90,
   "estado_match": "MATCH",
   "origen_match": "fuzzy",
   "created_at": "2026-07-14T11:28:58.064449+00:00"
  },
  {
   "id": "29a269c3-4b40-40bf-aa44-16dc9c2c5eef",
   "presupuesto_id": "ee48cb06-b8cc-4c95-ad47-24a5d9fdfd36",
   "texto_original": "UNION SIMPLE FUSION 50 MM 22325051 TIGRE",
   "texto_normalizado": "union simple fusion 50 mm 22325051 tigre",
   "marca": null,
   "unidad": null,
   "cantidad": 1.0,
   "precio": 1305.49,
   "codigo_material": "INSTS054",
   "pendiente_id": null,
   "score_match": 100,
   "estado_match": "MATCH",
   "origen_match": "fuzzy",
   "created_at": "2026-07-14T11:28:58.064449+00:00"
  },
  {
   "id": "4eda1fd4-cfd5-4ba1-b4bc-c42b6a1d76c7",
   "presupuesto_id": "ee48cb06-b8cc-4c95-ad47-24a5d9fdfd36",
   "texto_original": "REJA MARCO DE ACERO 15X15 RMA1515 WATERPLAST",
   "texto_normalizado": "reja marco de acero 15x15 rma1515 waterplast",
   "marca": null,
   "unidad": null,
   "cantidad": 4.0,
   "precio": 4922.67,
   "codigo_material": "INSTS008",
   "pendiente_id": null,
   "score_match": 100,
   "estado_match": "MATCH",
   "origen_match": "fuzzy",
   "created_at": "2026-07-14T11:28:58.064449+00:00"
  },
  {
   "id": "2c74a7b8-312b-4abf-a982-aba98342e107",
   "presupuesto_id": "ee48cb06-b8cc-4c95-ad47-24a5d9fdfd36",
   "texto_original": "MARCO BRONCE C/TAPA ACERO INOX 15X15 DURATOP",
   "texto_normalizado": "marco bronce c/tapa acero inox 15x15 duratop",
   "marca": null,
   "unidad": null,
   "cantidad": 3.0,
   "precio": 6278.91,
   "codigo_material": "INSTS008",
   "pendiente_id": null,
   "score_match": 86,
   "estado_match": "MATCH",
   "origen_match": "fuzzy",
   "created_at": "2026-07-14T11:28:58.064449+00:00"
  },
  {
   "id": "5fd56001-f985-4c2c-a443-19269e536763",
   "presupuesto_id": "ee48cb06-b8cc-4c95-ad47-24a5d9fdfd36",
   "texto_original": "CUPLA PVC SOLDABLE 50 22406280 TIGRE",
   "texto_normalizado": "cupla pvc soldable 50 22406280 tigre",
   "marca": null,
   "unidad": null,
   "cantidad": 24.0,
   "precio": 855.84,
   "codigo_material": "INSTS054",
   "pendiente_id": null,
   "score_match": 100,
   "estado_match": "MATCH",
   "origen_match": "fuzzy",
   "created_at": "2026-07-14T11:28:58.064449+00:00"
  },
  {
   "id": "5061f4b0-0c55-4f0e-b37b-495498d42bd0",
   "presupuesto_id": "ee48cb06-b8cc-4c95-ad47-24a5d9fdfd36",
   "texto_original": "DESAGUE AQUA LINEAL 70CM CLAS.BRIL ATRIM",
   "texto_normalizado": "desague aqua lineal 70cm clas.bril atrim",
   "marca": null,
   "unidad": null,
   "cantidad": 3.0,
   "precio": 113465.29,
   "codigo_material": "INSTS009",
   "pendiente_id": null,
   "score_match": 76,
   "estado_match": "REVISAR",
   "origen_match": "fuzzy",
   "created_at": "2026-07-14T11:28:58.064449+00:00"
  },
  {
   "id": "b488da6a-1b21-434d-9fd5-5013df0b0920",
   "presupuesto_id": "ee48cb06-b8cc-4c95-ad47-24a5d9fdfd36",
   "texto_original": "TUBO PPR3-PN 20 20MM IRAM 17010018 TIGRE",
   "texto_normalizado": "tubo ppr3-pn 20 20mm iram 17010018 tigre",
   "marca": null,
   "unidad": null,
   "cantidad": 19.0,
   "precio": 3268.01,
   "codigo_material": "INSTE077",
   "pendiente_id": null,
   "score_match": 83,
   "estado_match": "REVISAR",
   "origen_match": "fuzzy",
   "created_at": "2026-07-14T11:28:58.064449+00:00"
  },
  {
   "id": "8e354275-61c2-4b83-89b4-3e33ea86fbfa",
   "presupuesto_id": "ee48cb06-b8cc-4c95-ad47-24a5d9fdfd36",
   "texto_original": "TUBO PPR3-PN 20 25MM IRAM 17010034 TIGRE",
   "texto_normalizado": "tubo ppr3-pn 20 25mm iram 17010034 tigre",
   "marca": null,
   "unidad": null,
   "cantidad": 36.0,
   "precio": 4743.75,
   "codigo_material": "INSTE077",
   "pendiente_id": null,
   "score_match": 83,
   "estado_match": "REVISAR",
   "origen_match": "fuzzy",
   "created_at": "2026-07-14T11:28:58.064449+00:00"
  },
  {
   "id": "49df4d58-7c0b-43e5-bb22-250dd5fc0ec9",
   "presupuesto_id": "ee48cb06-b8cc-4c95-ad47-24a5d9fdfd36",
   "texto_original": "TUBO PPR3-PN 20 32MM IRAM 17010050 TIGRE",
   "texto_normalizado": "tubo ppr3-pn 20 32mm iram 17010050 tigre",
   "marca": null,
   "unidad": null,
   "cantidad": 24.0,
   "precio": 7377.19,
   "codigo_material": "INSTE077",
   "pendiente_id": null,
   "score_match": 83,
   "estado_match": "REVISAR",
   "origen_match": "fuzzy",
   "created_at": "2026-07-14T11:28:58.064449+00:00"
  },
  {
   "id": "316ff52e-b31a-44f0-8a16-b6238e4ef846",
   "presupuesto_id": "ee48cb06-b8cc-4c95-ad47-24a5d9fdfd36",
   "texto_original": "TUBO PPR3-PN 20 50MM IRAM 17010093 TIGRE",
   "texto_normalizado": "tubo ppr3-pn 20 50mm iram 17010093 tigre",
   "marca": null,
   "unidad": null,
   "cantidad": 6.0,
   "precio": 19755.38,
   "codigo_material": "INSTE077",
   "pendiente_id": null,
   "score_match": 83,
   "estado_match": "REVISAR",
   "origen_match": "fuzzy",
   "created_at": "2026-07-14T11:28:58.064449+00:00"
  },
  {
   "id": "3299a908-c8d1-49e0-9760-11a884daf527",
   "presupuesto_id": "ee48cb06-b8cc-4c95-ad47-24a5d9fdfd36",
   "texto_original": "TE NORMAL FUSION 20X20X20 22322508 TIGRE",
   "texto_normalizado": "te normal fusion 20x20x20 22322508 tigre",
   "marca": null,
   "unidad": null,
   "cantidad": 8.0,
   "precio": 259.77,
   "codigo_material": "INSTS093",
   "pendiente_id": null,
   "score_match": 76,
   "estado_match": "REVISAR",
   "origen_match": "fuzzy",
   "created_at": "2026-07-14T11:28:58.064449+00:00"
  },
  {
   "id": "e337b0bc-1e4b-497d-8366-223457979d21",
   "presupuesto_id": "ee48cb06-b8cc-4c95-ad47-24a5d9fdfd36",
   "texto_original": "REJA C/MARCO FUNDIDO LINEA PRO 15X15 WATERPLAST",
   "texto_normalizado": "reja c/marco fundido linea pro 15x15 waterplast",
   "marca": null,
   "unidad": null,
   "cantidad": 2.0,
   "precio": 10444.05,
   "codigo_material": "INSTS008",
   "pendiente_id": null,
   "score_match": 77,
   "estado_match": "REVISAR",
   "origen_match": "fuzzy",
   "created_at": "2026-07-14T11:28:58.064449+00:00"
  },
  {
   "id": "e9be898b-3567-4fe1-894d-606500931427",
   "presupuesto_id": "ee48cb06-b8cc-4c95-ad47-24a5d9fdfd36",
   "texto_original": "CAÑO SOLDABLE PVC 50X2.4X6M CL.10 JP TIGRE",
   "texto_normalizado": "caño soldable pvc 50x2.4x6m cl.10 jp tigre",
   "marca": null,
   "unidad": null,
   "cantidad": 40.0,
   "precio": 20220.51,
   "codigo_material": "INSTE077",
   "pendiente_id": null,
   "score_match": 73,
   "estado_match": "REVISAR",
   "origen_match": "fuzzy",
   "created_at": "2026-07-14T11:28:58.064449+00:00"
  },
  {
   "id": "ec5bfdfa-1069-486c-a599-1df305c3440a",
   "presupuesto_id": "ee48cb06-b8cc-4c95-ad47-24a5d9fdfd36",
   "texto_original": "CAJA MEDIDOR DE AGUA DOM 40X20X18 CM WATERPLAST",
   "texto_normalizado": "caja medidor de agua dom 40x20x18 cm waterplast",
   "marca": null,
   "unidad": null,
   "cantidad": 7.0,
   "precio": 10643.62,
   "codigo_material": "INSTS008",
   "pendiente_id": null,
   "score_match": 73,
   "estado_match": "REVISAR",
   "origen_match": "fuzzy",
   "created_at": "2026-07-14T11:28:58.064449+00:00"
  },
  {
   "id": "d96a0bca-c8f1-40fb-8d1a-83941366d4a1",
   "presupuesto_id": "59bf9dd8-b4cf-4761-ad05-2c9c736282d7",
   "texto_original": "108 TEJUELA DE 20 MM REFRECTARIO",
   "texto_normalizado": "108 tejuela de 20 mm refrectario",
   "marca": null,
   "unidad": null,
   "cantidad": 208.0,
   "precio": 1350.87,
   "codigo_material": "CONS125",
   "pendiente_id": null,
   "score_match": 100,
   "estado_match": "MATCH",
   "origen_match": "fuzzy",
   "created_at": "2026-07-22T15:26:35.304226+00:00"
  },
  {
   "id": "0b48a388-0276-47b0-9f82-aacfad293c61",
   "presupuesto_id": "31c93516-ece3-4ec3-9a7c-89c927cd7dd1",
   "texto_original": "HIERRO ADN 12mm",
   "texto_normalizado": "hierro adn 12mm",
   "marca": null,
   "unidad": null,
   "cantidad": 8.0,
   "precio": 20493.03,
   "codigo_material": "A006",
   "pendiente_id": null,
   "score_match": 100,
   "estado_match": "MATCH",
   "origen_match": "fuzzy",
   "created_at": "2026-07-22T15:26:58.113247+00:00"
  },
  {
   "id": "3e0d0ee4-2028-49bc-9d50-d4379c52d96c",
   "presupuesto_id": "f073b605-d5d8-428a-9c3d-fe9d30ffc04d",
   "texto_original": "TORNILLO ALAS 8X1 1/4\" (BOLSA X 100)- TEL",
   "texto_normalizado": "tornillo alas 8x1 1/4\" (bolsa x 100)- tel",
   "marca": null,
   "unidad": null,
   "cantidad": 158.0,
   "precio": 3310.69,
   "codigo_material": "T005",
   "pendiente_id": null,
   "score_match": 100,
   "estado_match": "CONFIRMADO",
   "origen_match": "usuario",
   "created_at": "2026-07-14T00:46:32.666314+00:00"
  },
  {
   "id": "589a2b2c-df18-43f9-a1c4-2d420fb5bf94",
   "presupuesto_id": "f073b605-d5d8-428a-9c3d-fe9d30ffc04d",
   "texto_original": "CANTONERA DE PVC CON MALLA DE FIBRA DE",
   "texto_normalizado": "cantonera de pvc con malla de fibra de",
   "marca": null,
   "unidad": null,
   "cantidad": 179.0,
   "precio": 2054.28,
   "codigo_material": "TER545",
   "pendiente_id": null,
   "score_match": 93,
   "estado_match": "CONFIRMADO",
   "origen_match": "usuario",
   "created_at": "2026-07-14T00:46:32.666314+00:00"
  },
  {
   "id": "61b1b86f-a8a0-485f-b0ea-64c4b98c4a9f",
   "presupuesto_id": "836af4a1-ec4e-4079-bfbf-7ce6a1ff8374",
   "texto_original": "FLEXIBLE MALLA ACERO 1/2 X 30",
   "texto_normalizado": "flexible malla acero 1/2 x 30",
   "marca": null,
   "unidad": null,
   "cantidad": 14.0,
   "precio": 4296.53,
   "codigo_material": "INSTS183",
   "pendiente_id": null,
   "score_match": 85,
   "estado_match": "CONFIRMADO",
   "origen_match": "usuario",
   "created_at": "2026-07-13T23:16:39.56214+00:00"
  },
  {
   "id": "1eee6f1e-b597-42d7-bf46-49024441cc54",
   "presupuesto_id": "836af4a1-ec4e-4079-bfbf-7ce6a1ff8374",
   "texto_original": "GAS CONEX. FLEXIBLE 1/2 X 30 DINAT",
   "texto_normalizado": "gas conex. flexible 1/2 x 30 dinat",
   "marca": null,
   "unidad": null,
   "cantidad": 2.0,
   "precio": 11598.24,
   "codigo_material": "INSTS202",
   "pendiente_id": null,
   "score_match": 86,
   "estado_match": "CONFIRMADO",
   "origen_match": "usuario",
   "created_at": "2026-07-13T23:16:39.56214+00:00"
  },
  {
   "id": "d29f9fda-3a82-4bce-adec-cc2920f7a745",
   "presupuesto_id": "836af4a1-ec4e-4079-bfbf-7ce6a1ff8374",
   "texto_original": "TORNILLO INODORO 22X80 CROMO",
   "texto_normalizado": "tornillo inodoro 22x80 cromo",
   "marca": null,
   "unidad": null,
   "cantidad": 4.0,
   "precio": 762.67,
   "codigo_material": "TER427",
   "pendiente_id": null,
   "score_match": 88,
   "estado_match": "CONFIRMADO",
   "origen_match": "usuario",
   "created_at": "2026-07-13T23:16:39.56214+00:00"
  },
  {
   "id": "62c02597-1ce0-49de-8a45-6cb3750f2d78",
   "presupuesto_id": "836af4a1-ec4e-4079-bfbf-7ce6a1ff8374",
   "texto_original": "ARO SUPLEMENTARIO C/CERA IDEAL",
   "texto_normalizado": "aro suplementario c/cera ideal",
   "marca": null,
   "unidad": null,
   "cantidad": 2.0,
   "precio": 9132.15,
   "codigo_material": "TER427",
   "pendiente_id": null,
   "score_match": 64,
   "estado_match": "CONFIRMADO",
   "origen_match": "usuario",
   "created_at": "2026-07-13T23:16:39.56214+00:00"
  },
  {
   "id": "20709239-6bbc-4bc1-822c-b185888eceb8",
   "presupuesto_id": "c9a33791-3d5b-4769-8179-2e4696b2e98e",
   "texto_original": "CODO A 90 RH 25 X 3/4 ACQUA",
   "texto_normalizado": "codo a 90 rh 25 x 3/4 acqua",
   "marca": null,
   "unidad": null,
   "cantidad": 2.0,
   "precio": 3863.49,
   "codigo_material": "INSTS188",
   "pendiente_id": null,
   "score_match": 100,
   "estado_match": "CONFIRMADO",
   "origen_match": "usuario",
   "created_at": "2026-07-13T23:16:41.843508+00:00"
  },
  {
   "id": "0db5ccbf-42da-418f-a250-31a2b9a0904d",
   "presupuesto_id": "c9a33791-3d5b-4769-8179-2e4696b2e98e",
   "texto_original": "FLEX MALLA INOX 1/2 X 30 M/FIJO (450283)",
   "texto_normalizado": "flex malla inox 1/2 x 30 m/fijo (450283)",
   "marca": null,
   "unidad": null,
   "cantidad": 14.0,
   "precio": 2162.8,
   "codigo_material": "INSTS183",
   "pendiente_id": null,
   "score_match": 86,
   "estado_match": "CONFIRMADO",
   "origen_match": "usuario",
   "created_at": "2026-07-13T23:16:41.843508+00:00"
  },
  {
   "id": "15452d7d-5376-411d-868b-793fbbef73a2",
   "presupuesto_id": "c9a33791-3d5b-4769-8179-2e4696b2e98e",
   "texto_original": "CAFIC FLEXIBLE APROB 1/2 X 30 CM",
   "texto_normalizado": "cafic flexible aprob 1/2 x 30 cm",
   "marca": null,
   "unidad": null,
   "cantidad": 2.0,
   "precio": 12430.66,
   "codigo_material": "INSTS202",
   "pendiente_id": null,
   "score_match": 87,
   "estado_match": "CONFIRMADO",
   "origen_match": "usuario",
   "created_at": "2026-07-13T23:16:41.843508+00:00"
  },
  {
   "id": "900e04a6-3b4c-40ce-9a5b-a328cb3634b0",
   "presupuesto_id": "836af4a1-ec4e-4079-bfbf-7ce6a1ff8374",
   "texto_original": "ASIENTO INODORO BARI TKX TRAFUL OFERTA",
   "texto_normalizado": "asiento inodoro bari tkx traful oferta",
   "marca": null,
   "unidad": null,
   "cantidad": 2.0,
   "precio": 33481.1,
   "codigo_material": "TER430",
   "pendiente_id": null,
   "score_match": 85,
   "estado_match": "CONFIRMADO",
   "origen_match": "usuario",
   "created_at": "2026-07-13T23:16:39.56214+00:00"
  },
  {
   "id": "d16c0f6b-eb53-4dad-9359-51cf8bbb3b19",
   "presupuesto_id": "c9a33791-3d5b-4769-8179-2e4696b2e98e",
   "texto_original": "TORNILLO P/INODORO COMPLETO 22 X 80",
   "texto_normalizado": "tornillo p/inodoro completo 22 x 80",
   "marca": null,
   "unidad": null,
   "cantidad": 2.0,
   "precio": 835.36,
   "codigo_material": "TER427",
   "pendiente_id": "17932229-4702-4ad0-8bb1-66b09a2158df",
   "score_match": 73,
   "estado_match": "REVISAR",
   "origen_match": "fuzzy",
   "created_at": "2026-07-13T23:16:41.843508+00:00"
  },
  {
   "id": "69fd74e2-416e-4d28-9250-bba03825cb82",
   "presupuesto_id": "c9a33791-3d5b-4769-8179-2e4696b2e98e",
   "texto_original": "TORNILLO P/INODORO COMPLETO 22 X 60",
   "texto_normalizado": "tornillo p/inodoro completo 22 x 60",
   "marca": null,
   "unidad": null,
   "cantidad": 2.0,
   "precio": 688.52,
   "codigo_material": "TER427",
   "pendiente_id": "29552156-1fde-47e2-ade4-3ce00f16c0c4",
   "score_match": 70,
   "estado_match": "REVISAR",
   "origen_match": "fuzzy",
   "created_at": "2026-07-13T23:16:41.843508+00:00"
  },
  {
   "id": "026d6127-1b12-4ec2-acee-d85c3b4da770",
   "presupuesto_id": "ffc7ed3d-56cc-4336-8f05-aa90045ef83a",
   "texto_original": "SINTEPLAST BASE COAT NF X 25 KG",
   "texto_normalizado": "sinteplast base coat nf x 25 kg",
   "marca": null,
   "unidad": null,
   "cantidad": 93.0,
   "precio": 23169.0,
   "codigo_material": "TER482",
   "pendiente_id": null,
   "score_match": 78,
   "estado_match": "CONFIRMADO",
   "origen_match": "usuario",
   "created_at": "2026-07-13T23:41:02.735926+00:00"
  },
  {
   "id": "36258252-cc20-4823-9ed6-46067af9e90a",
   "presupuesto_id": "b606c5b4-3b5e-4cad-9f06-72f587fbb524",
   "texto_original": "TORN ALAS P/SUPERB. 8 x 1-1/4 x 100 u",
   "texto_normalizado": "torn alas p/superb. 8 x 1-1/4 x 100 u",
   "marca": null,
   "unidad": null,
   "cantidad": 1.0,
   "precio": 4265.67,
   "codigo_material": "T005",
   "pendiente_id": null,
   "score_match": 100,
   "estado_match": "CONFIRMADO",
   "origen_match": "usuario",
   "created_at": "2026-07-14T00:43:15.407+00:00"
  },
  {
   "id": "5f46ed12-2362-4eba-ada2-724e331836d0",
   "presupuesto_id": "f073b605-d5d8-428a-9c3d-fe9d30ffc04d",
   "texto_original": "ARANDELA SOPORTE EIFS",
   "texto_normalizado": "arandela soporte eifs",
   "marca": null,
   "unidad": null,
   "cantidad": 3200.0,
   "precio": 30.96,
   "codigo_material": "TER114",
   "pendiente_id": null,
   "score_match": 84,
   "estado_match": "CONFIRMADO",
   "origen_match": "usuario",
   "created_at": "2026-07-14T00:46:32.666314+00:00"
  },
  {
   "id": "d8247afe-3cf8-4e9a-9e0f-a6a165047ae5",
   "presupuesto_id": "b606c5b4-3b5e-4cad-9f06-72f587fbb524",
   "texto_original": "TORN ALAS P/SUPERB. 10 x 1-5/8 x 100 u",
   "texto_normalizado": "torn alas p/superb. 10 x 1-5/8 x 100 u",
   "marca": null,
   "unidad": null,
   "cantidad": 1.0,
   "precio": 6635.84,
   "codigo_material": "T005",
   "pendiente_id": "00145c03-b573-4638-9ac3-06117c574147",
   "score_match": 76,
   "estado_match": "REVISAR",
   "origen_match": "fuzzy",
   "created_at": "2026-07-14T00:43:15.407+00:00"
  },
  {
   "id": "e652270e-1caf-4d1e-bc1a-a7e006b40185",
   "presupuesto_id": "c4fc4453-61d5-446d-aac1-cceca3e4cf2b",
   "texto_original": "BASE COAT GRANITEX",
   "texto_normalizado": "base coat granitex",
   "marca": null,
   "unidad": null,
   "cantidad": 93.0,
   "precio": 15837.1,
   "codigo_material": "TER482",
   "pendiente_id": null,
   "score_match": 76,
   "estado_match": "CONFIRMADO",
   "origen_match": "usuario",
   "created_at": "2026-07-14T00:46:33.684124+00:00"
  },
  {
   "id": "6dd18e2b-60cf-4c3b-af1e-00ae58466c68",
   "presupuesto_id": "290caab4-ee21-4c20-a829-970345df6f1d",
   "texto_original": "BASE COAT ANCLAFLEX X 25KG",
   "texto_normalizado": "base coat anclaflex x 25kg",
   "marca": null,
   "unidad": null,
   "cantidad": 93.0,
   "precio": 19221.72,
   "codigo_material": "TER482",
   "pendiente_id": null,
   "score_match": 100,
   "estado_match": "CONFIRMADO",
   "origen_match": "usuario",
   "created_at": "2026-07-14T01:00:35.919053+00:00"
  },
  {
   "id": "d9d41003-36e8-4072-bb5d-d7009d35fc52",
   "presupuesto_id": "f2c3bfb4-a079-4fd7-8233-f726eb74588d",
   "texto_original": "WEBER.THERM BASE COAT GRIS X25KG",
   "texto_normalizado": "weber.therm base coat gris x25kg",
   "marca": null,
   "unidad": null,
   "cantidad": 93.0,
   "precio": 55615.42,
   "codigo_material": "TER482",
   "pendiente_id": null,
   "score_match": 100,
   "estado_match": "MATCH",
   "origen_match": "fuzzy",
   "created_at": "2026-07-22T15:26:09.526663+00:00"
  },
  {
   "id": "7c55c6f2-9e8e-423a-b62c-910d96273724",
   "presupuesto_id": "54c44c3f-183c-4f85-a852-fa01c003f594",
   "texto_original": "WEBER REV BASE COAT GRIS X 30 KG",
   "texto_normalizado": "weber rev base coat gris x 30 kg",
   "marca": null,
   "unidad": null,
   "cantidad": 93.0,
   "precio": 38325.03,
   "codigo_material": "TER482",
   "pendiente_id": null,
   "score_match": 100,
   "estado_match": "MATCH",
   "origen_match": "fuzzy",
   "created_at": "2026-07-22T15:26:11.014334+00:00"
  },
  {
   "id": "8ae5f2cd-0801-480f-a176-a2ebe76b2fe5",
   "presupuesto_id": "ce3a5ba0-68e0-4d94-a8c6-e990728f66d3",
   "texto_original": "CAJA ALAS C/ESTRIAS - 8 X 1,1/4 X 6.000",
   "texto_normalizado": "caja alas c/estrias - 8 x 1,1/4 x 6.000",
   "marca": null,
   "unidad": null,
   "cantidad": 2.0,
   "precio": 348804.08,
   "codigo_material": "T005",
   "pendiente_id": null,
   "score_match": 73,
   "estado_match": "CONFIRMADO",
   "origen_match": "usuario",
   "created_at": "2026-07-14T01:41:30.295985+00:00"
  },
  {
   "id": "bb96fa1e-8765-48ce-9d17-9dd9c4e85f8b",
   "presupuesto_id": "ce3a5ba0-68e0-4d94-a8c6-e990728f66d3",
   "texto_original": "ALAS CON ESTRIAS 8 X 1,1/4 X 100",
   "texto_normalizado": "alas con estrias 8 x 1,1/4 x 100",
   "marca": null,
   "unidad": null,
   "cantidad": 38.0,
   "precio": 6260.58,
   "codigo_material": "T005",
   "pendiente_id": null,
   "score_match": 73,
   "estado_match": "CONFIRMADO",
   "origen_match": "usuario",
   "created_at": "2026-07-14T01:41:30.295985+00:00"
  },
  {
   "id": "286d76d4-71c7-4558-9ccc-0e2f465b2b4b",
   "presupuesto_id": "ce3a5ba0-68e0-4d94-a8c6-e990728f66d3",
   "texto_original": "ARANDELA EPS X 100",
   "texto_normalizado": "arandela eps x 100",
   "marca": null,
   "unidad": null,
   "cantidad": 32.0,
   "precio": 3453.73,
   "codigo_material": "TER114",
   "pendiente_id": null,
   "score_match": 83,
   "estado_match": "CONFIRMADO",
   "origen_match": "usuario",
   "created_at": "2026-07-14T01:41:30.295985+00:00"
  },
  {
   "id": "92e4e3c2-497b-4318-bd98-9280a4fe1f93",
   "presupuesto_id": "ce3a5ba0-68e0-4d94-a8c6-e990728f66d3",
   "texto_original": "ARANDELA P/ HTT14 (C) (BARBIERI)",
   "texto_normalizado": "arandela p/ htt14 (c) (barbieri)",
   "marca": null,
   "unidad": null,
   "cantidad": 73.0,
   "precio": 400.25,
   "codigo_material": "TER114",
   "pendiente_id": "0be0582b-af5b-4319-8e86-99c331293740",
   "score_match": 76,
   "estado_match": "REVISAR",
   "origen_match": "fuzzy",
   "created_at": "2026-07-14T01:41:30.295985+00:00"
  },
  {
   "id": "2a5d58ae-9f43-4535-9a00-74109f5d8de3",
   "presupuesto_id": "3194629f-cf2a-47da-87c4-92dc0e71a30a",
   "texto_original": "1,00 LLAVE DE PASO CON ROSETA YMANIVELA CROMO 32MM FUSIOGAS $ 53.089,77 0,00 $",
   "texto_normalizado": "1,00 llave de paso con roseta ymanivela cromo 32mm fusiogas $ 53.089,77 0,00 $",
   "marca": null,
   "unidad": null,
   "cantidad": 1.0,
   "precio": 48045.04,
   "codigo_material": "INSTS187",
   "pendiente_id": null,
   "score_match": 87,
   "estado_match": "MATCH",
   "origen_match": "fuzzy",
   "created_at": "2026-07-14T11:28:53.988639+00:00"
  },
  {
   "id": "babe9069-c3d7-453d-9449-02b61243cb61",
   "presupuesto_id": "3194629f-cf2a-47da-87c4-92dc0e71a30a",
   "texto_original": "15,00 MALLA DE ADVERTENCIA X MT $ 1.188,09 0,00 $",
   "texto_normalizado": "15,00 malla de advertencia x mt $ 1.188,09 0,00 $",
   "marca": null,
   "unidad": null,
   "cantidad": 1.0,
   "precio": 16127.92,
   "codigo_material": "INSTS222",
   "pendiente_id": null,
   "score_match": 87,
   "estado_match": "MATCH",
   "origen_match": "fuzzy",
   "created_at": "2026-07-14T11:28:53.988639+00:00"
  },
  {
   "id": "be330924-7f23-41d1-aeb1-5113a1625fa8",
   "presupuesto_id": "3194629f-cf2a-47da-87c4-92dc0e71a30a",
   "texto_original": "2,00 FLEXIBLE DE GAS 1/2 X 30CM $ 1.856,40 0,00 $",
   "texto_normalizado": "2,00 flexible de gas 1/2 x 30cm $ 1.856,40 0,00 $",
   "marca": null,
   "unidad": null,
   "cantidad": 1.0,
   "precio": 3360.0,
   "codigo_material": "INSTS202",
   "pendiente_id": null,
   "score_match": 76,
   "estado_match": "REVISAR",
   "origen_match": "fuzzy",
   "created_at": "2026-07-14T11:28:53.988639+00:00"
  },
  {
   "id": "926a1478-3258-467a-aa62-964bf9565f78",
   "presupuesto_id": "0a5e78a7-e65e-4bfe-97cb-19132da30a71",
   "texto_original": "FLEX.MALLADO A.INOX. 1/2 X 35 LATYN AF2075 LATYN",
   "texto_normalizado": "flex.mallado a.inox. 1/2 x 35 latyn af2075 latyn",
   "marca": null,
   "unidad": null,
   "cantidad": 17.0,
   "precio": 2512.8,
   "codigo_material": "INSTS202",
   "pendiente_id": null,
   "score_match": 100,
   "estado_match": "MATCH",
   "origen_match": "fuzzy",
   "created_at": "2026-07-14T11:28:56.286309+00:00"
  },
  {
   "id": "1cf2a7a6-6fcc-4a4c-a783-c4c8ac72d94f",
   "presupuesto_id": "0a5e78a7-e65e-4bfe-97cb-19132da30a71",
   "texto_original": "FLEX.MALLADO A.INOX. 1/2 X 30 LATYN AF2075 LATYN",
   "texto_normalizado": "flex.mallado a.inox. 1/2 x 30 latyn af2075 latyn",
   "marca": null,
   "unidad": null,
   "cantidad": 7.0,
   "precio": 2418.4,
   "codigo_material": "INSTS202",
   "pendiente_id": null,
   "score_match": 100,
   "estado_match": "MATCH",
   "origen_match": "fuzzy",
   "created_at": "2026-07-14T11:28:56.286309+00:00"
  },
  {
   "id": "43d14902-ecc2-41bb-93fb-ac1cbf11c25d",
   "presupuesto_id": "0a5e78a7-e65e-4bfe-97cb-19132da30a71",
   "texto_original": "FLEXIBLE CAFIC P/GAS 1/2 X 30 DINATECNICA",
   "texto_normalizado": "flexible cafic p/gas 1/2 x 30 dinatecnica",
   "marca": null,
   "unidad": null,
   "cantidad": 2.0,
   "precio": 11291.65,
   "codigo_material": "INSTS202",
   "pendiente_id": null,
   "score_match": 87,
   "estado_match": "MATCH",
   "origen_match": "fuzzy",
   "created_at": "2026-07-14T11:28:56.286309+00:00"
  },
  {
   "id": "b3156519-b071-4204-91c8-5366014687b8",
   "presupuesto_id": "ee48cb06-b8cc-4c95-ad47-24a5d9fdfd36",
   "texto_original": "FLEX.MALLADO A.INOX. 1/2 X 35 LATYN AF2075 LATYN",
   "texto_normalizado": "flex.mallado a.inox. 1/2 x 35 latyn af2075 latyn",
   "marca": null,
   "unidad": null,
   "cantidad": 17.0,
   "precio": 2512.8,
   "codigo_material": "INSTS202",
   "pendiente_id": null,
   "score_match": 100,
   "estado_match": "MATCH",
   "origen_match": "fuzzy",
   "created_at": "2026-07-14T11:28:58.064449+00:00"
  },
  {
   "id": "7cd6054f-684a-4c33-9380-eca0f4fa40ea",
   "presupuesto_id": "ee48cb06-b8cc-4c95-ad47-24a5d9fdfd36",
   "texto_original": "FLEX.MALLADO A.INOX. 1/2 X 30 LATYN AF2075 LATYN",
   "texto_normalizado": "flex.mallado a.inox. 1/2 x 30 latyn af2075 latyn",
   "marca": null,
   "unidad": null,
   "cantidad": 7.0,
   "precio": 2418.4,
   "codigo_material": "INSTS202",
   "pendiente_id": null,
   "score_match": 100,
   "estado_match": "MATCH",
   "origen_match": "fuzzy",
   "created_at": "2026-07-14T11:28:58.064449+00:00"
  },
  {
   "id": "ab232e5a-3b2c-4cc5-86b1-a8d3ad4ca474",
   "presupuesto_id": "ee48cb06-b8cc-4c95-ad47-24a5d9fdfd36",
   "texto_original": "FLEXIBLE CAFIC P/GAS 1/2 X 30 DINATECNICA",
   "texto_normalizado": "flexible cafic p/gas 1/2 x 30 dinatecnica",
   "marca": null,
   "unidad": null,
   "cantidad": 2.0,
   "precio": 11291.65,
   "codigo_material": "INSTS202",
   "pendiente_id": null,
   "score_match": 87,
   "estado_match": "MATCH",
   "origen_match": "fuzzy",
   "created_at": "2026-07-14T11:28:58.064449+00:00"
  },
  {
   "id": "d041a351-c583-4991-8cd3-75917f7b6975",
   "presupuesto_id": "16107651-deed-4e23-bf64-1e52867a7e7d",
   "texto_original": "BASE COAT ANCLAFLEX MONOCOMPONENTE X 25 KG ANCLAF",
   "texto_normalizado": "base coat anclaflex monocomponente x 25 kg anclaf",
   "marca": null,
   "unidad": null,
   "cantidad": 93.0,
   "precio": 17750.45,
   "codigo_material": "TER482",
   "pendiente_id": null,
   "score_match": 100,
   "estado_match": "MATCH",
   "origen_match": "fuzzy",
   "created_at": "2026-07-22T15:26:44.658873+00:00"
  }
 ]
}